{"copyright":{"shortname":"copyright","emoji":"\u00a9","unicode":"U+00A9","name":"copyright sign"},"registered":{"shortname":"registered","emoji":"\u00ae","unicode":"U+00AE","name":"registered sign"},"bangbang":{"shortname":"bangbang","emoji":"\u203c","unicode":"U+203C","name":"double exclamation mark"},"interrobang":{"shortname":"interrobang","emoji":"\u2049","unicode":"U+2049","name":"exclamation question mark"},"tm":{"shortname":"tm","emoji":"\u2122","unicode":"U+2122","name":"trade mark sign"},"information_source":{"shortname":"information_source","emoji":"\u2139","unicode":"U+2139","name":"information source"},"left_right_arrow":{"shortname":"left_right_arrow","emoji":"\u2194","unicode":"U+2194","name":"left right arrow"},"arrow_up_down":{"shortname":"arrow_up_down","emoji":"\u2195","unicode":"U+2195","name":"up down arrow"},"arrow_upper_left":{"shortname":"arrow_upper_left","emoji":"\u2196","unicode":"U+2196","name":"north west arrow"},"arrow_upper_right":{"shortname":"arrow_upper_right","emoji":"\u2197","unicode":"U+2197","name":"north east arrow"},"arrow_lower_right":{"shortname":"arrow_lower_right","emoji":"\u2198","unicode":"U+2198","name":"south east arrow"},"arrow_lower_left":{"shortname":"arrow_lower_left","emoji":"\u2199","unicode":"U+2199","name":"south west arrow"},"leftwards_arrow_with_hook":{"shortname":"leftwards_arrow_with_hook","emoji":"\u21a9","unicode":"U+21A9","name":"leftwards arrow with hook"},"arrow_right_hook":{"shortname":"arrow_right_hook","emoji":"\u21aa","unicode":"U+21AA","name":"rightwards arrow with hook"},"watch":{"shortname":"watch","emoji":"\u231a","unicode":"U+231A","name":"watch"},"hourglass":{"shortname":"hourglass","emoji":"\u231b","unicode":"U+231B","name":"hourglass"},"fast_forward":{"shortname":"fast_forward","emoji":"\u23e9","unicode":"U+23E9","name":"black right-pointing double triangle"},"rewind":{"shortname":"rewind","emoji":"\u23ea","unicode":"U+23EA","name":"black left-pointing double triangle"},"arrow_double_up":{"shortname":"arrow_double_up","emoji":"\u23eb","unicode":"U+23EB","name":"black up-pointing double triangle"},"arrow_double_down":{"shortname":"arrow_double_down","emoji":"\u23ec","unicode":"U+23EC","name":"black down-pointing double triangle"},"alarm_clock":{"shortname":"alarm_clock","emoji":"\u23f0","unicode":"U+23F0","name":"alarm clock"},"hourglass_flowing_sand":{"shortname":"hourglass_flowing_sand","emoji":"\u23f3","unicode":"U+23F3","name":"hourglass with flowing sand"},"m":{"shortname":"m","emoji":"\u24c2","unicode":"U+24C2","name":"circled latin capital letter m"},"black_small_square":{"shortname":"black_small_square","emoji":"\u25aa","unicode":"U+25AA","name":"black small square"},"white_small_square":{"shortname":"white_small_square","emoji":"\u25ab","unicode":"U+25AB","name":"white small square"},"arrow_forward":{"shortname":"arrow_forward","emoji":"\u25b6","unicode":"U+25B6","name":"black right-pointing triangle"},"arrow_backward":{"shortname":"arrow_backward","emoji":"\u25c0","unicode":"U+25C0","name":"black left-pointing triangle"},"white_medium_square":{"shortname":"white_medium_square","emoji":"\u25fb","unicode":"U+25FB","name":"white medium square"},"black_medium_square":{"shortname":"black_medium_square","emoji":"\u25fc","unicode":"U+25FC","name":"black medium square"},"white_medium_small_square":{"shortname":"white_medium_small_square","emoji":"\u25fd","unicode":"U+25FD","name":"white medium small square"},"black_medium_small_square":{"shortname":"black_medium_small_square","emoji":"\u25fe","unicode":"U+25FE","name":"black medium small square"},"sunny":{"shortname":"sunny","emoji":"\u2600","unicode":"U+2600","name":"black sun with rays"},"cloud":{"shortname":"cloud","emoji":"\u2601","unicode":"U+2601","name":"cloud"},"phone":{"shortname":"phone","emoji":"\u260e","unicode":"U+260E","name":"black telephone"},"ballot_box_with_check":{"shortname":"ballot_box_with_check","emoji":"\u2611","unicode":"U+2611","name":"ballot box with check"},"umbrella":{"shortname":"umbrella","emoji":"\u2614","unicode":"U+2614","name":"umbrella with rain drops"},"coffee":{"shortname":"coffee","emoji":"\u2615","unicode":"U+2615","name":"hot beverage"},"point_up":{"shortname":"point_up","emoji":"\u261d","unicode":"U+261D","name":"white up pointing index"},"relaxed":{"shortname":"relaxed","emoji":"\u263a","unicode":"U+263A","name":"white smiling face"},"aries":{"shortname":"aries","emoji":"\u2648","unicode":"U+2648","name":"aries"},"taurus":{"shortname":"taurus","emoji":"\u2649","unicode":"U+2649","name":"taurus"},"gemini":{"shortname":"gemini","emoji":"\u264a","unicode":"U+264A","name":"gemini"},"cancer":{"shortname":"cancer","emoji":"\u264b","unicode":"U+264B","name":"cancer"},"leo":{"shortname":"leo","emoji":"\u264c","unicode":"U+264C","name":"leo"},"virgo":{"shortname":"virgo","emoji":"\u264d","unicode":"U+264D","name":"virgo"},"libra":{"shortname":"libra","emoji":"\u264e","unicode":"U+264E","name":"libra"},"scorpius":{"shortname":"scorpius","emoji":"\u264f","unicode":"U+264F","name":"scorpius"},"sagittarius":{"shortname":"sagittarius","emoji":"\u2650","unicode":"U+2650","name":"sagittarius"},"capricorn":{"shortname":"capricorn","emoji":"\u2651","unicode":"U+2651","name":"capricorn"},"aquarius":{"shortname":"aquarius","emoji":"\u2652","unicode":"U+2652","name":"aquarius"},"pisces":{"shortname":"pisces","emoji":"\u2653","unicode":"U+2653","name":"pisces"},"spades":{"shortname":"spades","emoji":"\u2660","unicode":"U+2660","name":"black spade suit"},"clubs":{"shortname":"clubs","emoji":"\u2663","unicode":"U+2663","name":"black club suit"},"hearts":{"shortname":"hearts","emoji":"\u2665","unicode":"U+2665","name":"black heart suit"},"diamonds":{"shortname":"diamonds","emoji":"\u2666","unicode":"U+2666","name":"black diamond suit"},"hotsprings":{"shortname":"hotsprings","emoji":"\u2668","unicode":"U+2668","name":"hot springs"},"recycle":{"shortname":"recycle","emoji":"\u267b","unicode":"U+267B","name":"black universal recycling symbol"},"wheelchair":{"shortname":"wheelchair","emoji":"\u267f","unicode":"U+267F","name":"wheelchair symbol"},"anchor":{"shortname":"anchor","emoji":"\u2693","unicode":"U+2693","name":"anchor"},"warning":{"shortname":"warning","emoji":"\u26a0","unicode":"U+26A0","name":"warning sign"},"zap":{"shortname":"zap","emoji":"\u26a1","unicode":"U+26A1","name":"high voltage sign"},"white_circle":{"shortname":"white_circle","emoji":"\u26aa","unicode":"U+26AA","name":"medium white circle"},"black_circle":{"shortname":"black_circle","emoji":"\u26ab","unicode":"U+26AB","name":"medium black circle"},"soccer":{"shortname":"soccer","emoji":"\u26bd","unicode":"U+26BD","name":"soccer ball"},"baseball":{"shortname":"baseball","emoji":"\u26be","unicode":"U+26BE","name":"baseball"},"snowman":{"shortname":"snowman","emoji":"\u26c4","unicode":"U+26C4","name":"snowman without snow"},"partly_sunny":{"shortname":"partly_sunny","emoji":"\u26c5","unicode":"U+26C5","name":"sun behind cloud"},"ophiuchus":{"shortname":"ophiuchus","emoji":"\u26ce","unicode":"U+26CE","name":"ophiuchus"},"no_entry":{"shortname":"no_entry","emoji":"\u26d4","unicode":"U+26D4","name":"no entry"},"church":{"shortname":"church","emoji":"\u26ea","unicode":"U+26EA","name":"church"},"fountain":{"shortname":"fountain","emoji":"\u26f2","unicode":"U+26F2","name":"fountain"},"golf":{"shortname":"golf","emoji":"\u26f3","unicode":"U+26F3","name":"flag in hole"},"boat":{"shortname":"boat","emoji":"\u26f5","unicode":"U+26F5","name":"sailboat"},"tent":{"shortname":"tent","emoji":"\u26fa","unicode":"U+26FA","name":"tent"},"fuelpump":{"shortname":"fuelpump","emoji":"\u26fd","unicode":"U+26FD","name":"fuel pump"},"scissors":{"shortname":"scissors","emoji":"\u2702","unicode":"U+2702","name":"black scissors"},"white_check_mark":{"shortname":"white_check_mark","emoji":"\u2705","unicode":"U+2705","name":"white heavy check mark"},"airplane":{"shortname":"airplane","emoji":"\u2708","unicode":"U+2708","name":"airplane"},"email":{"shortname":"email","emoji":"\u2709","unicode":"U+2709","name":"envelope"},"fist":{"shortname":"fist","emoji":"\u270a","unicode":"U+270A","name":"raised fist"},"hand":{"shortname":"hand","emoji":"\u270b","unicode":"U+270B","name":"raised hand"},"v":{"shortname":"v","emoji":"\u270c","unicode":"U+270C","name":"victory hand"},"pencil2":{"shortname":"pencil2","emoji":"\u270f","unicode":"U+270F","name":"pencil"},"black_nib":{"shortname":"black_nib","emoji":"\u2712","unicode":"U+2712","name":"black nib"},"heavy_check_mark":{"shortname":"heavy_check_mark","emoji":"\u2714","unicode":"U+2714","name":"heavy check mark"},"heavy_multiplication_x":{"shortname":"heavy_multiplication_x","emoji":"\u2716","unicode":"U+2716","name":"heavy multiplication x"},"sparkles":{"shortname":"sparkles","emoji":"\u2728","unicode":"U+2728","name":"sparkles"},"eight_spoked_asterisk":{"shortname":"eight_spoked_asterisk","emoji":"\u2733","unicode":"U+2733","name":"eight spoked asterisk"},"eight_pointed_black_star":{"shortname":"eight_pointed_black_star","emoji":"\u2734","unicode":"U+2734","name":"eight pointed black star"},"snowflake":{"shortname":"snowflake","emoji":"\u2744","unicode":"U+2744","name":"snowflake"},"sparkle":{"shortname":"sparkle","emoji":"\u2747","unicode":"U+2747","name":"sparkle"},"x":{"shortname":"x","emoji":"\u274c","unicode":"U+274C","name":"cross mark"},"negative_squared_cross_mark":{"shortname":"negative_squared_cross_mark","emoji":"\u274e","unicode":"U+274E","name":"negative squared cross mark"},"question":{"shortname":"question","emoji":"\u2753","unicode":"U+2753","name":"black question mark ornament"},"grey_question":{"shortname":"grey_question","emoji":"\u2754","unicode":"U+2754","name":"white question mark ornament"},"grey_exclamation":{"shortname":"grey_exclamation","emoji":"\u2755","unicode":"U+2755","name":"white exclamation mark ornament"},"exclamation":{"shortname":"exclamation","emoji":"\u2757","unicode":"U+2757","name":"heavy exclamation mark symbol"},"heart":{"shortname":"heart","emoji":"\u2764","unicode":"U+2764","name":"heavy black heart"},"heavy_plus_sign":{"shortname":"heavy_plus_sign","emoji":"\u2795","unicode":"U+2795","name":"heavy plus sign"},"heavy_minus_sign":{"shortname":"heavy_minus_sign","emoji":"\u2796","unicode":"U+2796","name":"heavy minus sign"},"heavy_division_sign":{"shortname":"heavy_division_sign","emoji":"\u2797","unicode":"U+2797","name":"heavy division sign"},"arrow_right":{"shortname":"arrow_right","emoji":"\u27a1","unicode":"U+27A1","name":"black rightwards arrow"},"curly_loop":{"shortname":"curly_loop","emoji":"\u27b0","unicode":"U+27B0","name":"curly loop"},"loop":{"shortname":"loop","emoji":null,"unicode":"U+27BF","name":"double curly loop"},"arrow_heading_up":{"shortname":"arrow_heading_up","emoji":"\u2934","unicode":"U+2934","name":"arrow pointing rightwards then curving upwards"},"arrow_heading_down":{"shortname":"arrow_heading_down","emoji":"\u2935","unicode":"U+2935","name":"arrow pointing rightwards then curving downwards"},"arrow_left":{"shortname":"arrow_left","emoji":"\u2b05","unicode":"U+2B05","name":"leftwards black arrow"},"arrow_up":{"shortname":"arrow_up","emoji":"\u2b06","unicode":"U+2B06","name":"upwards black arrow"},"arrow_down":{"shortname":"arrow_down","emoji":"\u2b07","unicode":"U+2B07","name":"downwards black arrow"},"black_large_square":{"shortname":"black_large_square","emoji":"\u2b1b","unicode":"U+2B1B","name":"black large square"},"white_large_square":{"shortname":"white_large_square","emoji":"\u2b1c","unicode":"U+2B1C","name":"white large square"},"star":{"shortname":"star","emoji":"\u2b50","unicode":"U+2B50","name":"white medium star"},"o":{"shortname":"o","emoji":"\u2b55","unicode":"U+2B55","name":"heavy large circle"},"wavy_dash":{"shortname":"wavy_dash","emoji":"\u3030","unicode":"U+3030","name":"wavy dash"},"part_alternation_mark":{"shortname":"part_alternation_mark","emoji":"\u303d","unicode":"U+303D","name":"part alternation mark"},"congratulations":{"shortname":"congratulations","emoji":"\u3297","unicode":"U+3297","name":"circled ideograph congratulation"},"secret":{"shortname":"secret","emoji":"\u3299","unicode":"U+3299","name":"circled ideograph secret"},"mahjong":{"shortname":"mahjong","emoji":"\ud83c\udc04","unicode":"U+1F004","name":"mahjong tile red dragon"},"black_joker":{"shortname":"black_joker","emoji":"\ud83c\udccf","unicode":"U+1F0CF","name":"playing card black joker"},"a":{"shortname":"a","emoji":"\ud83c\udd70","unicode":"U+1F170","name":"negative squared latin capital letter a"},"b":{"shortname":"b","emoji":"\ud83c\udd71","unicode":"U+1F171","name":"negative squared latin capital letter b"},"o2":{"shortname":"o2","emoji":"\ud83c\udd7e","unicode":"U+1F17E","name":"negative squared latin capital letter o"},"parking":{"shortname":"parking","emoji":"\ud83c\udd7f","unicode":"U+1F17F","name":"negative squared latin capital letter p"},"ab":{"shortname":"ab","emoji":"\ud83c\udd8e","unicode":"U+1F18E","name":"negative squared ab"},"cl":{"shortname":"cl","emoji":"\ud83c\udd91","unicode":"U+1F191","name":"squared cl"},"cool":{"shortname":"cool","emoji":"\ud83c\udd92","unicode":"U+1F192","name":"squared cool"},"free":{"shortname":"free","emoji":"\ud83c\udd93","unicode":"U+1F193","name":"squared free"},"id":{"shortname":"id","emoji":"\ud83c\udd94","unicode":"U+1F194","name":"squared id"},"new":{"shortname":"new","emoji":"\ud83c\udd95","unicode":"U+1F195","name":"squared new"},"ng":{"shortname":"ng","emoji":"\ud83c\udd96","unicode":"U+1F196","name":"squared ng"},"ok":{"shortname":"ok","emoji":"\ud83c\udd97","unicode":"U+1F197","name":"squared ok"},"sos":{"shortname":"sos","emoji":"\ud83c\udd98","unicode":"U+1F198","name":"squared sos"},"up":{"shortname":"up","emoji":"\ud83c\udd99","unicode":"U+1F199","name":"squared up with exclamation mark"},"vs":{"shortname":"vs","emoji":"\ud83c\udd9a","unicode":"U+1F19A","name":"squared vs"},"koko":{"shortname":"koko","emoji":"\ud83c\ude01","unicode":"U+1F201","name":"squared katakana koko"},"sa":{"shortname":"sa","emoji":"\ud83c\ude02","unicode":"U+1F202","name":"squared katakana sa"},"u7121":{"shortname":"u7121","emoji":"\ud83c\ude1a","unicode":"U+1F21A","name":"squared cjk unified ideograph-7121"},"u6307":{"shortname":"u6307","emoji":"\ud83c\ude2f","unicode":"U+1F22F","name":"squared cjk unified ideograph-6307"},"u7981":{"shortname":"u7981","emoji":"\ud83c\ude32","unicode":"U+1F232","name":"squared cjk unified ideograph-7981"},"u7a7a":{"shortname":"u7a7a","emoji":"\ud83c\ude33","unicode":"U+1F233","name":"squared cjk unified ideograph-7a7a"},"u5408":{"shortname":"u5408","emoji":"\ud83c\ude34","unicode":"U+1F234","name":"squared cjk unified ideograph-5408"},"u6e80":{"shortname":"u6e80","emoji":"\ud83c\ude35","unicode":"U+1F235","name":"squared cjk unified ideograph-6e80"},"u6709":{"shortname":"u6709","emoji":"\ud83c\ude36","unicode":"U+1F236","name":"squared cjk unified ideograph-6709"},"u6708":{"shortname":"u6708","emoji":"\ud83c\ude37","unicode":"U+1F237","name":"squared cjk unified ideograph-6708"},"u7533":{"shortname":"u7533","emoji":"\ud83c\ude38","unicode":"U+1F238","name":"squared cjk unified ideograph-7533"},"u5272":{"shortname":"u5272","emoji":"\ud83c\ude39","unicode":"U+1F239","name":"squared cjk unified ideograph-5272"},"u55b6":{"shortname":"u55b6","emoji":"\ud83c\ude3a","unicode":"U+1F23A","name":"squared cjk unified ideograph-55b6"},"ideograph_advantage":{"shortname":"ideograph_advantage","emoji":"\ud83c\ude50","unicode":"U+1F250","name":"circled ideograph advantage"},"accept":{"shortname":"accept","emoji":"\ud83c\ude51","unicode":"U+1F251","name":"circled ideograph accept"},"cyclone":{"shortname":"cyclone","emoji":"\ud83c\udf00","unicode":"U+1F300","name":"cyclone"},"foggy":{"shortname":"foggy","emoji":"\ud83c\udf01","unicode":"U+1F301","name":"foggy"},"closed_umbrella":{"shortname":"closed_umbrella","emoji":"\ud83c\udf02","unicode":"U+1F302","name":"closed umbrella"},"night_with_stars":{"shortname":"night_with_stars","emoji":"\ud83c\udf03","unicode":"U+1F303","name":"night with stars"},"sunrise_over_mountains":{"shortname":"sunrise_over_mountains","emoji":"\ud83c\udf04","unicode":"U+1F304","name":"sunrise over mountains"},"sunrise":{"shortname":"sunrise","emoji":"\ud83c\udf05","unicode":"U+1F305","name":"sunrise"},"city_sunset":{"shortname":"city_sunset","emoji":"\ud83c\udf06","unicode":"U+1F306","name":"cityscape at dusk"},"city_sunrise":{"shortname":"city_sunrise","emoji":"\ud83c\udf07","unicode":"U+1F307","name":"sunset over buildings"},"rainbow":{"shortname":"rainbow","emoji":"\ud83c\udf08","unicode":"U+1F308","name":"rainbow"},"bridge_at_night":{"shortname":"bridge_at_night","emoji":"\ud83c\udf09","unicode":"U+1F309","name":"bridge at night"},"ocean":{"shortname":"ocean","emoji":"\ud83c\udf0a","unicode":"U+1F30A","name":"water wave"},"volcano":{"shortname":"volcano","emoji":"\ud83c\udf0b","unicode":"U+1F30B","name":"volcano"},"milky_way":{"shortname":"milky_way","emoji":"\ud83c\udf0c","unicode":"U+1F30C","name":"milky way"},"earth_africa":{"shortname":"earth_africa","emoji":"\ud83c\udf0d","unicode":"U+1F30D","name":"earth globe europe-africa"},"earth_americas":{"shortname":"earth_americas","emoji":"\ud83c\udf0e","unicode":"U+1F30E","name":"earth globe americas"},"earth_asia":{"shortname":"earth_asia","emoji":"\ud83c\udf0f","unicode":"U+1F30F","name":"earth globe asia-australia"},"globe_with_meridians":{"shortname":"globe_with_meridians","emoji":"\ud83c\udf10","unicode":"U+1F310","name":"globe with meridians"},"new_moon":{"shortname":"new_moon","emoji":"\ud83c\udf11","unicode":"U+1F311","name":"new moon symbol"},"waxing_crescent_moon":{"shortname":"waxing_crescent_moon","emoji":"\ud83c\udf12","unicode":"U+1F312","name":"waxing crescent moon symbol"},"first_quarter_moon":{"shortname":"first_quarter_moon","emoji":"\ud83c\udf13","unicode":"U+1F313","name":"first quarter moon symbol"},"moon":{"shortname":"moon","emoji":"\ud83c\udf14","unicode":"U+1F314","name":"waxing gibbous moon symbol"},"full_moon":{"shortname":"full_moon","emoji":"\ud83c\udf15","unicode":"U+1F315","name":"full moon symbol"},"waning_gibbous_moon":{"shortname":"waning_gibbous_moon","emoji":"\ud83c\udf16","unicode":"U+1F316","name":"waning gibbous moon symbol"},"last_quarter_moon":{"shortname":"last_quarter_moon","emoji":"\ud83c\udf17","unicode":"U+1F317","name":"last quarter moon symbol"},"waning_crescent_moon":{"shortname":"waning_crescent_moon","emoji":"\ud83c\udf18","unicode":"U+1F318","name":"waning crescent moon symbol"},"crescent_moon":{"shortname":"crescent_moon","emoji":"\ud83c\udf19","unicode":"U+1F319","name":"crescent moon"},"new_moon_with_face":{"shortname":"new_moon_with_face","emoji":"\ud83c\udf1a","unicode":"U+1F31A","name":"new moon with face"},"first_quarter_moon_with_face":{"shortname":"first_quarter_moon_with_face","emoji":"\ud83c\udf1b","unicode":"U+1F31B","name":"first quarter moon with face"},"last_quarter_moon_with_face":{"shortname":"last_quarter_moon_with_face","emoji":"\ud83c\udf1c","unicode":"U+1F31C","name":"last quarter moon with face"},"full_moon_with_face":{"shortname":"full_moon_with_face","emoji":"\ud83c\udf1d","unicode":"U+1F31D","name":"full moon with face"},"sun_with_face":{"shortname":"sun_with_face","emoji":"\ud83c\udf1e","unicode":"U+1F31E","name":"sun with face"},"star2":{"shortname":"star2","emoji":"\ud83c\udf1f","unicode":"U+1F31F","name":"glowing star"},"stars":{"shortname":"stars","emoji":"\ud83c\udf20","unicode":"U+1F320","name":"shooting star"},"chestnut":{"shortname":"chestnut","emoji":"\ud83c\udf30","unicode":"U+1F330","name":"chestnut"},"seedling":{"shortname":"seedling","emoji":"\ud83c\udf31","unicode":"U+1F331","name":"seedling"},"evergreen_tree":{"shortname":"evergreen_tree","emoji":"\ud83c\udf32","unicode":"U+1F332","name":"evergreen tree"},"deciduous_tree":{"shortname":"deciduous_tree","emoji":"\ud83c\udf33","unicode":"U+1F333","name":"deciduous tree"},"palm_tree":{"shortname":"palm_tree","emoji":"\ud83c\udf34","unicode":"U+1F334","name":"palm tree"},"cactus":{"shortname":"cactus","emoji":"\ud83c\udf35","unicode":"U+1F335","name":"cactus"},"tulip":{"shortname":"tulip","emoji":"\ud83c\udf37","unicode":"U+1F337","name":"tulip"},"cherry_blossom":{"shortname":"cherry_blossom","emoji":"\ud83c\udf38","unicode":"U+1F338","name":"cherry blossom"},"rose":{"shortname":"rose","emoji":"\ud83c\udf39","unicode":"U+1F339","name":"rose"},"hibiscus":{"shortname":"hibiscus","emoji":"\ud83c\udf3a","unicode":"U+1F33A","name":"hibiscus"},"sunflower":{"shortname":"sunflower","emoji":"\ud83c\udf3b","unicode":"U+1F33B","name":"sunflower"},"blossom":{"shortname":"blossom","emoji":"\ud83c\udf3c","unicode":"U+1F33C","name":"blossom"},"corn":{"shortname":"corn","emoji":"\ud83c\udf3d","unicode":"U+1F33D","name":"ear of maize"},"ear_of_rice":{"shortname":"ear_of_rice","emoji":"\ud83c\udf3e","unicode":"U+1F33E","name":"ear of rice"},"herb":{"shortname":"herb","emoji":"\ud83c\udf3f","unicode":"U+1F33F","name":"herb"},"four_leaf_clover":{"shortname":"four_leaf_clover","emoji":"\ud83c\udf40","unicode":"U+1F340","name":"four leaf clover"},"maple_leaf":{"shortname":"maple_leaf","emoji":"\ud83c\udf41","unicode":"U+1F341","name":"maple leaf"},"fallen_leaf":{"shortname":"fallen_leaf","emoji":"\ud83c\udf42","unicode":"U+1F342","name":"fallen leaf"},"leaves":{"shortname":"leaves","emoji":"\ud83c\udf43","unicode":"U+1F343","name":"leaf fluttering in wind"},"mushroom":{"shortname":"mushroom","emoji":"\ud83c\udf44","unicode":"U+1F344","name":"mushroom"},"tomato":{"shortname":"tomato","emoji":"\ud83c\udf45","unicode":"U+1F345","name":"tomato"},"eggplant":{"shortname":"eggplant","emoji":"\ud83c\udf46","unicode":"U+1F346","name":"aubergine"},"grapes":{"shortname":"grapes","emoji":"\ud83c\udf47","unicode":"U+1F347","name":"grapes"},"melon":{"shortname":"melon","emoji":"\ud83c\udf48","unicode":"U+1F348","name":"melon"},"watermelon":{"shortname":"watermelon","emoji":"\ud83c\udf49","unicode":"U+1F349","name":"watermelon"},"tangerine":{"shortname":"tangerine","emoji":"\ud83c\udf4a","unicode":"U+1F34A","name":"tangerine"},"lemon":{"shortname":"lemon","emoji":"\ud83c\udf4b","unicode":"U+1F34B","name":"lemon"},"banana":{"shortname":"banana","emoji":"\ud83c\udf4c","unicode":"U+1F34C","name":"banana"},"pineapple":{"shortname":"pineapple","emoji":"\ud83c\udf4d","unicode":"U+1F34D","name":"pineapple"},"apple":{"shortname":"apple","emoji":"\ud83c\udf4e","unicode":"U+1F34E","name":"red apple"},"green_apple":{"shortname":"green_apple","emoji":"\ud83c\udf4f","unicode":"U+1F34F","name":"green apple"},"pear":{"shortname":"pear","emoji":"\ud83c\udf50","unicode":"U+1F350","name":"pear"},"peach":{"shortname":"peach","emoji":"\ud83c\udf51","unicode":"U+1F351","name":"peach"},"cherries":{"shortname":"cherries","emoji":"\ud83c\udf52","unicode":"U+1F352","name":"cherries"},"strawberry":{"shortname":"strawberry","emoji":"\ud83c\udf53","unicode":"U+1F353","name":"strawberry"},"hamburger":{"shortname":"hamburger","emoji":"\ud83c\udf54","unicode":"U+1F354","name":"hamburger"},"pizza":{"shortname":"pizza","emoji":"\ud83c\udf55","unicode":"U+1F355","name":"slice of pizza"},"meat_on_bone":{"shortname":"meat_on_bone","emoji":"\ud83c\udf56","unicode":"U+1F356","name":"meat on bone"},"poultry_leg":{"shortname":"poultry_leg","emoji":"\ud83c\udf57","unicode":"U+1F357","name":"poultry leg"},"rice_cracker":{"shortname":"rice_cracker","emoji":"\ud83c\udf58","unicode":"U+1F358","name":"rice cracker"},"rice_ball":{"shortname":"rice_ball","emoji":"\ud83c\udf59","unicode":"U+1F359","name":"rice ball"},"rice":{"shortname":"rice","emoji":"\ud83c\udf5a","unicode":"U+1F35A","name":"cooked rice"},"curry":{"shortname":"curry","emoji":"\ud83c\udf5b","unicode":"U+1F35B","name":"curry and rice"},"ramen":{"shortname":"ramen","emoji":"\ud83c\udf5c","unicode":"U+1F35C","name":"steaming bowl"},"spaghetti":{"shortname":"spaghetti","emoji":"\ud83c\udf5d","unicode":"U+1F35D","name":"spaghetti"},"bread":{"shortname":"bread","emoji":"\ud83c\udf5e","unicode":"U+1F35E","name":"bread"},"fries":{"shortname":"fries","emoji":"\ud83c\udf5f","unicode":"U+1F35F","name":"french fries"},"sweet_potato":{"shortname":"sweet_potato","emoji":"\ud83c\udf60","unicode":"U+1F360","name":"roasted sweet potato"},"dango":{"shortname":"dango","emoji":"\ud83c\udf61","unicode":"U+1F361","name":"dango"},"oden":{"shortname":"oden","emoji":"\ud83c\udf62","unicode":"U+1F362","name":"oden"},"sushi":{"shortname":"sushi","emoji":"\ud83c\udf63","unicode":"U+1F363","name":"sushi"},"fried_shrimp":{"shortname":"fried_shrimp","emoji":"\ud83c\udf64","unicode":"U+1F364","name":"fried shrimp"},"fish_cake":{"shortname":"fish_cake","emoji":"\ud83c\udf65","unicode":"U+1F365","name":"fish cake with swirl design"},"icecream":{"shortname":"icecream","emoji":"\ud83c\udf66","unicode":"U+1F366","name":"soft ice cream"},"shaved_ice":{"shortname":"shaved_ice","emoji":"\ud83c\udf67","unicode":"U+1F367","name":"shaved ice"},"ice_cream":{"shortname":"ice_cream","emoji":"\ud83c\udf68","unicode":"U+1F368","name":"ice cream"},"doughnut":{"shortname":"doughnut","emoji":"\ud83c\udf69","unicode":"U+1F369","name":"doughnut"},"cookie":{"shortname":"cookie","emoji":"\ud83c\udf6a","unicode":"U+1F36A","name":"cookie"},"chocolate_bar":{"shortname":"chocolate_bar","emoji":"\ud83c\udf6b","unicode":"U+1F36B","name":"chocolate bar"},"candy":{"shortname":"candy","emoji":"\ud83c\udf6c","unicode":"U+1F36C","name":"candy"},"lollipop":{"shortname":"lollipop","emoji":"\ud83c\udf6d","unicode":"U+1F36D","name":"lollipop"},"custard":{"shortname":"custard","emoji":"\ud83c\udf6e","unicode":"U+1F36E","name":"custard"},"honey_pot":{"shortname":"honey_pot","emoji":"\ud83c\udf6f","unicode":"U+1F36F","name":"honey pot"},"cake":{"shortname":"cake","emoji":"\ud83c\udf70","unicode":"U+1F370","name":"shortcake"},"bento":{"shortname":"bento","emoji":"\ud83c\udf71","unicode":"U+1F371","name":"bento box"},"stew":{"shortname":"stew","emoji":"\ud83c\udf72","unicode":"U+1F372","name":"pot of food"},"egg":{"shortname":"egg","emoji":"\ud83c\udf73","unicode":"U+1F373","name":"cooking"},"fork_and_knife":{"shortname":"fork_and_knife","emoji":"\ud83c\udf74","unicode":"U+1F374","name":"fork and knife"},"tea":{"shortname":"tea","emoji":"\ud83c\udf75","unicode":"U+1F375","name":"teacup without handle"},"sake":{"shortname":"sake","emoji":"\ud83c\udf76","unicode":"U+1F376","name":"sake bottle and cup"},"wine_glass":{"shortname":"wine_glass","emoji":"\ud83c\udf77","unicode":"U+1F377","name":"wine glass"},"cocktail":{"shortname":"cocktail","emoji":"\ud83c\udf78","unicode":"U+1F378","name":"cocktail glass"},"tropical_drink":{"shortname":"tropical_drink","emoji":"\ud83c\udf79","unicode":"U+1F379","name":"tropical drink"},"beer":{"shortname":"beer","emoji":"\ud83c\udf7a","unicode":"U+1F37A","name":"beer mug"},"beers":{"shortname":"beers","emoji":"\ud83c\udf7b","unicode":"U+1F37B","name":"clinking beer mugs"},"baby_bottle":{"shortname":"baby_bottle","emoji":"\ud83c\udf7c","unicode":"U+1F37C","name":"baby bottle"},"ribbon":{"shortname":"ribbon","emoji":"\ud83c\udf80","unicode":"U+1F380","name":"ribbon"},"gift":{"shortname":"gift","emoji":"\ud83c\udf81","unicode":"U+1F381","name":"wrapped present"},"birthday":{"shortname":"birthday","emoji":"\ud83c\udf82","unicode":"U+1F382","name":"birthday cake"},"jack_o_lantern":{"shortname":"jack_o_lantern","emoji":"\ud83c\udf83","unicode":"U+1F383","name":"jack-o-lantern"},"christmas_tree":{"shortname":"christmas_tree","emoji":"\ud83c\udf84","unicode":"U+1F384","name":"christmas tree"},"santa":{"shortname":"santa","emoji":"\ud83c\udf85","unicode":"U+1F385","name":"father christmas"},"fireworks":{"shortname":"fireworks","emoji":"\ud83c\udf86","unicode":"U+1F386","name":"fireworks"},"sparkler":{"shortname":"sparkler","emoji":"\ud83c\udf87","unicode":"U+1F387","name":"firework sparkler"},"balloon":{"shortname":"balloon","emoji":"\ud83c\udf88","unicode":"U+1F388","name":"balloon"},"tada":{"shortname":"tada","emoji":"\ud83c\udf89","unicode":"U+1F389","name":"party popper"},"confetti_ball":{"shortname":"confetti_ball","emoji":"\ud83c\udf8a","unicode":"U+1F38A","name":"confetti ball"},"tanabata_tree":{"shortname":"tanabata_tree","emoji":"\ud83c\udf8b","unicode":"U+1F38B","name":"tanabata tree"},"crossed_flags":{"shortname":"crossed_flags","emoji":"\ud83c\udf8c","unicode":"U+1F38C","name":"crossed flags"},"bamboo":{"shortname":"bamboo","emoji":"\ud83c\udf8d","unicode":"U+1F38D","name":"pine decoration"},"dolls":{"shortname":"dolls","emoji":"\ud83c\udf8e","unicode":"U+1F38E","name":"japanese dolls"},"flags":{"shortname":"flags","emoji":"\ud83c\udf8f","unicode":"U+1F38F","name":"carp streamer"},"wind_chime":{"shortname":"wind_chime","emoji":"\ud83c\udf90","unicode":"U+1F390","name":"wind chime"},"rice_scene":{"shortname":"rice_scene","emoji":"\ud83c\udf91","unicode":"U+1F391","name":"moon viewing ceremony"},"school_satchel":{"shortname":"school_satchel","emoji":"\ud83c\udf92","unicode":"U+1F392","name":"school satchel"},"mortar_board":{"shortname":"mortar_board","emoji":"\ud83c\udf93","unicode":"U+1F393","name":"graduation cap"},"carousel_horse":{"shortname":"carousel_horse","emoji":"\ud83c\udfa0","unicode":"U+1F3A0","name":"carousel horse"},"ferris_wheel":{"shortname":"ferris_wheel","emoji":"\ud83c\udfa1","unicode":"U+1F3A1","name":"ferris wheel"},"roller_coaster":{"shortname":"roller_coaster","emoji":"\ud83c\udfa2","unicode":"U+1F3A2","name":"roller coaster"},"fishing_pole_and_fish":{"shortname":"fishing_pole_and_fish","emoji":"\ud83c\udfa3","unicode":"U+1F3A3","name":"fishing pole and fish"},"microphone":{"shortname":"microphone","emoji":"\ud83c\udfa4","unicode":"U+1F3A4","name":"microphone"},"movie_camera":{"shortname":"movie_camera","emoji":"\ud83c\udfa5","unicode":"U+1F3A5","name":"movie camera"},"cinema":{"shortname":"cinema","emoji":"\ud83c\udfa6","unicode":"U+1F3A6","name":"cinema"},"headphones":{"shortname":"headphones","emoji":"\ud83c\udfa7","unicode":"U+1F3A7","name":"headphone"},"art":{"shortname":"art","emoji":"\ud83c\udfa8","unicode":"U+1F3A8","name":"artist palette"},"tophat":{"shortname":"tophat","emoji":"\ud83c\udfa9","unicode":"U+1F3A9","name":"top hat"},"circus_tent":{"shortname":"circus_tent","emoji":"\ud83c\udfaa","unicode":"U+1F3AA","name":"circus tent"},"ticket":{"shortname":"ticket","emoji":"\ud83c\udfab","unicode":"U+1F3AB","name":"ticket"},"clapper":{"shortname":"clapper","emoji":"\ud83c\udfac","unicode":"U+1F3AC","name":"clapper board"},"performing_arts":{"shortname":"performing_arts","emoji":"\ud83c\udfad","unicode":"U+1F3AD","name":"performing arts"},"video_game":{"shortname":"video_game","emoji":"\ud83c\udfae","unicode":"U+1F3AE","name":"video game"},"dart":{"shortname":"dart","emoji":"\ud83c\udfaf","unicode":"U+1F3AF","name":"direct hit"},"slot_machine":{"shortname":"slot_machine","emoji":"\ud83c\udfb0","unicode":"U+1F3B0","name":"slot machine"},"8ball":{"shortname":"8ball","emoji":"\ud83c\udfb1","unicode":"U+1F3B1","name":"billiards"},"game_die":{"shortname":"game_die","emoji":"\ud83c\udfb2","unicode":"U+1F3B2","name":"game die"},"bowling":{"shortname":"bowling","emoji":"\ud83c\udfb3","unicode":"U+1F3B3","name":"bowling"},"flower_playing_cards":{"shortname":"flower_playing_cards","emoji":"\ud83c\udfb4","unicode":"U+1F3B4","name":"flower playing cards"},"musical_note":{"shortname":"musical_note","emoji":"\ud83c\udfb5","unicode":"U+1F3B5","name":"musical note"},"notes":{"shortname":"notes","emoji":"\ud83c\udfb6","unicode":"U+1F3B6","name":"multiple musical notes"},"saxophone":{"shortname":"saxophone","emoji":"\ud83c\udfb7","unicode":"U+1F3B7","name":"saxophone"},"guitar":{"shortname":"guitar","emoji":"\ud83c\udfb8","unicode":"U+1F3B8","name":"guitar"},"musical_keyboard":{"shortname":"musical_keyboard","emoji":"\ud83c\udfb9","unicode":"U+1F3B9","name":"musical keyboard"},"trumpet":{"shortname":"trumpet","emoji":"\ud83c\udfba","unicode":"U+1F3BA","name":"trumpet"},"violin":{"shortname":"violin","emoji":"\ud83c\udfbb","unicode":"U+1F3BB","name":"violin"},"musical_score":{"shortname":"musical_score","emoji":"\ud83c\udfbc","unicode":"U+1F3BC","name":"musical score"},"running_shirt_with_sash":{"shortname":"running_shirt_with_sash","emoji":"\ud83c\udfbd","unicode":"U+1F3BD","name":"running shirt with sash"},"tennis":{"shortname":"tennis","emoji":"\ud83c\udfbe","unicode":"U+1F3BE","name":"tennis racquet and ball"},"ski":{"shortname":"ski","emoji":"\ud83c\udfbf","unicode":"U+1F3BF","name":"ski and ski boot"},"basketball":{"shortname":"basketball","emoji":"\ud83c\udfc0","unicode":"U+1F3C0","name":"basketball and hoop"},"checkered_flag":{"shortname":"checkered_flag","emoji":"\ud83c\udfc1","unicode":"U+1F3C1","name":"chequered flag"},"snowboarder":{"shortname":"snowboarder","emoji":"\ud83c\udfc2","unicode":"U+1F3C2","name":"snowboarder"},"runner":{"shortname":"runner","emoji":"\ud83c\udfc3","unicode":"U+1F3C3","name":"runner"},"surfer":{"shortname":"surfer","emoji":"\ud83c\udfc4","unicode":"U+1F3C4","name":"surfer"},"trophy":{"shortname":"trophy","emoji":"\ud83c\udfc6","unicode":"U+1F3C6","name":"trophy"},"horse_racing":{"shortname":"horse_racing","emoji":"\ud83c\udfc7","unicode":"U+1F3C7","name":"horse racing"},"football":{"shortname":"football","emoji":"\ud83c\udfc8","unicode":"U+1F3C8","name":"american football"},"rugby_football":{"shortname":"rugby_football","emoji":"\ud83c\udfc9","unicode":"U+1F3C9","name":"rugby football"},"swimmer":{"shortname":"swimmer","emoji":"\ud83c\udfca","unicode":"U+1F3CA","name":"swimmer"},"house":{"shortname":"house","emoji":"\ud83c\udfe0","unicode":"U+1F3E0","name":"house building"},"house_with_garden":{"shortname":"house_with_garden","emoji":"\ud83c\udfe1","unicode":"U+1F3E1","name":"house with garden"},"office":{"shortname":"office","emoji":"\ud83c\udfe2","unicode":"U+1F3E2","name":"office building"},"post_office":{"shortname":"post_office","emoji":"\ud83c\udfe3","unicode":"U+1F3E3","name":"japanese post office"},"european_post_office":{"shortname":"european_post_office","emoji":"\ud83c\udfe4","unicode":"U+1F3E4","name":"european post office"},"hospital":{"shortname":"hospital","emoji":"\ud83c\udfe5","unicode":"U+1F3E5","name":"hospital"},"bank":{"shortname":"bank","emoji":"\ud83c\udfe6","unicode":"U+1F3E6","name":"bank"},"atm":{"shortname":"atm","emoji":"\ud83c\udfe7","unicode":"U+1F3E7","name":"automated teller machine"},"hotel":{"shortname":"hotel","emoji":"\ud83c\udfe8","unicode":"U+1F3E8","name":"hotel"},"love_hotel":{"shortname":"love_hotel","emoji":"\ud83c\udfe9","unicode":"U+1F3E9","name":"love hotel"},"convenience_store":{"shortname":"convenience_store","emoji":"\ud83c\udfea","unicode":"U+1F3EA","name":"convenience store"},"school":{"shortname":"school","emoji":"\ud83c\udfeb","unicode":"U+1F3EB","name":"school"},"department_store":{"shortname":"department_store","emoji":"\ud83c\udfec","unicode":"U+1F3EC","name":"department store"},"factory":{"shortname":"factory","emoji":"\ud83c\udfed","unicode":"U+1F3ED","name":"factory"},"izakaya_lantern":{"shortname":"izakaya_lantern","emoji":"\ud83c\udfee","unicode":"U+1F3EE","name":"izakaya lantern"},"japanese_castle":{"shortname":"japanese_castle","emoji":"\ud83c\udfef","unicode":"U+1F3EF","name":"japanese castle"},"european_castle":{"shortname":"european_castle","emoji":"\ud83c\udff0","unicode":"U+1F3F0","name":"european castle"},"rat":{"shortname":"rat","emoji":"\ud83d\udc00","unicode":"U+1F400","name":"rat"},"mouse2":{"shortname":"mouse2","emoji":"\ud83d\udc01","unicode":"U+1F401","name":"mouse"},"ox":{"shortname":"ox","emoji":"\ud83d\udc02","unicode":"U+1F402","name":"ox"},"water_buffalo":{"shortname":"water_buffalo","emoji":"\ud83d\udc03","unicode":"U+1F403","name":"water buffalo"},"cow2":{"shortname":"cow2","emoji":"\ud83d\udc04","unicode":"U+1F404","name":"cow"},"tiger2":{"shortname":"tiger2","emoji":"\ud83d\udc05","unicode":"U+1F405","name":"tiger"},"leopard":{"shortname":"leopard","emoji":"\ud83d\udc06","unicode":"U+1F406","name":"leopard"},"rabbit2":{"shortname":"rabbit2","emoji":"\ud83d\udc07","unicode":"U+1F407","name":"rabbit"},"cat2":{"shortname":"cat2","emoji":"\ud83d\udc08","unicode":"U+1F408","name":"cat"},"dragon":{"shortname":"dragon","emoji":"\ud83d\udc09","unicode":"U+1F409","name":"dragon"},"crocodile":{"shortname":"crocodile","emoji":"\ud83d\udc0a","unicode":"U+1F40A","name":"crocodile"},"whale2":{"shortname":"whale2","emoji":"\ud83d\udc0b","unicode":"U+1F40B","name":"whale"},"snail":{"shortname":"snail","emoji":"\ud83d\udc0c","unicode":"U+1F40C","name":"snail"},"snake":{"shortname":"snake","emoji":"\ud83d\udc0d","unicode":"U+1F40D","name":"snake"},"racehorse":{"shortname":"racehorse","emoji":"\ud83d\udc0e","unicode":"U+1F40E","name":"horse"},"ram":{"shortname":"ram","emoji":"\ud83d\udc0f","unicode":"U+1F40F","name":"ram"},"goat":{"shortname":"goat","emoji":"\ud83d\udc10","unicode":"U+1F410","name":"goat"},"sheep":{"shortname":"sheep","emoji":"\ud83d\udc11","unicode":"U+1F411","name":"sheep"},"monkey":{"shortname":"monkey","emoji":"\ud83d\udc12","unicode":"U+1F412","name":"monkey"},"rooster":{"shortname":"rooster","emoji":"\ud83d\udc13","unicode":"U+1F413","name":"rooster"},"chicken":{"shortname":"chicken","emoji":"\ud83d\udc14","unicode":"U+1F414","name":"chicken"},"dog2":{"shortname":"dog2","emoji":"\ud83d\udc15","unicode":"U+1F415","name":"dog"},"pig2":{"shortname":"pig2","emoji":"\ud83d\udc16","unicode":"U+1F416","name":"pig"},"boar":{"shortname":"boar","emoji":"\ud83d\udc17","unicode":"U+1F417","name":"boar"},"elephant":{"shortname":"elephant","emoji":"\ud83d\udc18","unicode":"U+1F418","name":"elephant"},"octopus":{"shortname":"octopus","emoji":"\ud83d\udc19","unicode":"U+1F419","name":"octopus"},"shell":{"shortname":"shell","emoji":"\ud83d\udc1a","unicode":"U+1F41A","name":"spiral shell"},"bug":{"shortname":"bug","emoji":"\ud83d\udc1b","unicode":"U+1F41B","name":"bug"},"ant":{"shortname":"ant","emoji":"\ud83d\udc1c","unicode":"U+1F41C","name":"ant"},"bee":{"shortname":"bee","emoji":"\ud83d\udc1d","unicode":"U+1F41D","name":"honeybee"},"beetle":{"shortname":"beetle","emoji":"\ud83d\udc1e","unicode":"U+1F41E","name":"lady beetle"},"fish":{"shortname":"fish","emoji":"\ud83d\udc1f","unicode":"U+1F41F","name":"fish"},"tropical_fish":{"shortname":"tropical_fish","emoji":"\ud83d\udc20","unicode":"U+1F420","name":"tropical fish"},"blowfish":{"shortname":"blowfish","emoji":"\ud83d\udc21","unicode":"U+1F421","name":"blowfish"},"turtle":{"shortname":"turtle","emoji":"\ud83d\udc22","unicode":"U+1F422","name":"turtle"},"hatching_chick":{"shortname":"hatching_chick","emoji":"\ud83d\udc23","unicode":"U+1F423","name":"hatching chick"},"baby_chick":{"shortname":"baby_chick","emoji":"\ud83d\udc24","unicode":"U+1F424","name":"baby chick"},"hatched_chick":{"shortname":"hatched_chick","emoji":"\ud83d\udc25","unicode":"U+1F425","name":"front-facing baby chick"},"bird":{"shortname":"bird","emoji":"\ud83d\udc26","unicode":"U+1F426","name":"bird"},"penguin":{"shortname":"penguin","emoji":"\ud83d\udc27","unicode":"U+1F427","name":"penguin"},"koala":{"shortname":"koala","emoji":"\ud83d\udc28","unicode":"U+1F428","name":"koala"},"poodle":{"shortname":"poodle","emoji":"\ud83d\udc29","unicode":"U+1F429","name":"poodle"},"dromedary_camel":{"shortname":"dromedary_camel","emoji":"\ud83d\udc2a","unicode":"U+1F42A","name":"dromedary camel"},"camel":{"shortname":"camel","emoji":"\ud83d\udc2b","unicode":"U+1F42B","name":"bactrian camel"},"dolphin":{"shortname":"dolphin","emoji":"\ud83d\udc2c","unicode":"U+1F42C","name":"dolphin"},"mouse":{"shortname":"mouse","emoji":"\ud83d\udc2d","unicode":"U+1F42D","name":"mouse face"},"cow":{"shortname":"cow","emoji":"\ud83d\udc2e","unicode":"U+1F42E","name":"cow face"},"tiger":{"shortname":"tiger","emoji":"\ud83d\udc2f","unicode":"U+1F42F","name":"tiger face"},"rabbit":{"shortname":"rabbit","emoji":"\ud83d\udc30","unicode":"U+1F430","name":"rabbit face"},"cat":{"shortname":"cat","emoji":"\ud83d\udc31","unicode":"U+1F431","name":"cat face"},"dragon_face":{"shortname":"dragon_face","emoji":"\ud83d\udc32","unicode":"U+1F432","name":"dragon face"},"whale":{"shortname":"whale","emoji":"\ud83d\udc33","unicode":"U+1F433","name":"spouting whale"},"horse":{"shortname":"horse","emoji":"\ud83d\udc34","unicode":"U+1F434","name":"horse face"},"monkey_face":{"shortname":"monkey_face","emoji":"\ud83d\udc35","unicode":"U+1F435","name":"monkey face"},"dog":{"shortname":"dog","emoji":"\ud83d\udc36","unicode":"U+1F436","name":"dog face"},"pig":{"shortname":"pig","emoji":"\ud83d\udc37","unicode":"U+1F437","name":"pig face"},"frog":{"shortname":"frog","emoji":"\ud83d\udc38","unicode":"U+1F438","name":"frog face"},"hamster":{"shortname":"hamster","emoji":"\ud83d\udc39","unicode":"U+1F439","name":"hamster face"},"wolf":{"shortname":"wolf","emoji":"\ud83d\udc3a","unicode":"U+1F43A","name":"wolf face"},"bear":{"shortname":"bear","emoji":"\ud83d\udc3b","unicode":"U+1F43B","name":"bear face"},"panda_face":{"shortname":"panda_face","emoji":"\ud83d\udc3c","unicode":"U+1F43C","name":"panda face"},"pig_nose":{"shortname":"pig_nose","emoji":"\ud83d\udc3d","unicode":"U+1F43D","name":"pig nose"},"feet":{"shortname":"feet","emoji":"\ud83d\udc3e","unicode":"U+1F43E","name":"paw prints"},"eyes":{"shortname":"eyes","emoji":"\ud83d\udc40","unicode":"U+1F440","name":"eyes"},"ear":{"shortname":"ear","emoji":"\ud83d\udc42","unicode":"U+1F442","name":"ear"},"nose":{"shortname":"nose","emoji":"\ud83d\udc43","unicode":"U+1F443","name":"nose"},"lips":{"shortname":"lips","emoji":"\ud83d\udc44","unicode":"U+1F444","name":"mouth"},"tongue":{"shortname":"tongue","emoji":"\ud83d\udc45","unicode":"U+1F445","name":"tongue"},"point_up_2":{"shortname":"point_up_2","emoji":"\ud83d\udc46","unicode":"U+1F446","name":"white up pointing backhand index"},"point_down":{"shortname":"point_down","emoji":"\ud83d\udc47","unicode":"U+1F447","name":"white down pointing backhand index"},"point_left":{"shortname":"point_left","emoji":"\ud83d\udc48","unicode":"U+1F448","name":"white left pointing backhand index"},"point_right":{"shortname":"point_right","emoji":"\ud83d\udc49","unicode":"U+1F449","name":"white right pointing backhand index"},"facepunch":{"shortname":"facepunch","emoji":"\ud83d\udc4a","unicode":"U+1F44A","name":"fisted hand sign"},"wave":{"shortname":"wave","emoji":"\ud83d\udc4b","unicode":"U+1F44B","name":"waving hand sign"},"ok_hand":{"shortname":"ok_hand","emoji":"\ud83d\udc4c","unicode":"U+1F44C","name":"ok hand sign"},"+1":{"shortname":"+1","emoji":"\ud83d\udc4d","unicode":"U+1F44D","name":"thumbs up sign"},"-1":{"shortname":"-1","emoji":"\ud83d\udc4e","unicode":"U+1F44E","name":"thumbs down sign"},"clap":{"shortname":"clap","emoji":"\ud83d\udc4f","unicode":"U+1F44F","name":"clapping hands sign"},"open_hands":{"shortname":"open_hands","emoji":"\ud83d\udc50","unicode":"U+1F450","name":"open hands sign"},"crown":{"shortname":"crown","emoji":"\ud83d\udc51","unicode":"U+1F451","name":"crown"},"womans_hat":{"shortname":"womans_hat","emoji":"\ud83d\udc52","unicode":"U+1F452","name":"womans hat"},"eyeglasses":{"shortname":"eyeglasses","emoji":"\ud83d\udc53","unicode":"U+1F453","name":"eyeglasses"},"necktie":{"shortname":"necktie","emoji":"\ud83d\udc54","unicode":"U+1F454","name":"necktie"},"shirt":{"shortname":"shirt","emoji":"\ud83d\udc55","unicode":"U+1F455","name":"t-shirt"},"jeans":{"shortname":"jeans","emoji":"\ud83d\udc56","unicode":"U+1F456","name":"jeans"},"dress":{"shortname":"dress","emoji":"\ud83d\udc57","unicode":"U+1F457","name":"dress"},"kimono":{"shortname":"kimono","emoji":"\ud83d\udc58","unicode":"U+1F458","name":"kimono"},"bikini":{"shortname":"bikini","emoji":"\ud83d\udc59","unicode":"U+1F459","name":"bikini"},"womans_clothes":{"shortname":"womans_clothes","emoji":"\ud83d\udc5a","unicode":"U+1F45A","name":"womans clothes"},"purse":{"shortname":"purse","emoji":"\ud83d\udc5b","unicode":"U+1F45B","name":"purse"},"handbag":{"shortname":"handbag","emoji":"\ud83d\udc5c","unicode":"U+1F45C","name":"handbag"},"pouch":{"shortname":"pouch","emoji":"\ud83d\udc5d","unicode":"U+1F45D","name":"pouch"},"mans_shoe":{"shortname":"mans_shoe","emoji":"\ud83d\udc5e","unicode":"U+1F45E","name":"mans shoe"},"athletic_shoe":{"shortname":"athletic_shoe","emoji":"\ud83d\udc5f","unicode":"U+1F45F","name":"athletic shoe"},"high_heel":{"shortname":"high_heel","emoji":"\ud83d\udc60","unicode":"U+1F460","name":"high-heeled shoe"},"sandal":{"shortname":"sandal","emoji":"\ud83d\udc61","unicode":"U+1F461","name":"womans sandal"},"boot":{"shortname":"boot","emoji":"\ud83d\udc62","unicode":"U+1F462","name":"womans boots"},"footprints":{"shortname":"footprints","emoji":"\ud83d\udc63","unicode":"U+1F463","name":"footprints"},"bust_in_silhouette":{"shortname":"bust_in_silhouette","emoji":"\ud83d\udc64","unicode":"U+1F464","name":"bust in silhouette"},"busts_in_silhouette":{"shortname":"busts_in_silhouette","emoji":"\ud83d\udc65","unicode":"U+1F465","name":"busts in silhouette"},"boy":{"shortname":"boy","emoji":"\ud83d\udc66","unicode":"U+1F466","name":"boy"},"girl":{"shortname":"girl","emoji":"\ud83d\udc67","unicode":"U+1F467","name":"girl"},"man":{"shortname":"man","emoji":"\ud83d\udc68","unicode":"U+1F468","name":"man"},"woman":{"shortname":"woman","emoji":"\ud83d\udc69","unicode":"U+1F469","name":"woman"},"family":{"shortname":"family","emoji":"\ud83d\udc6a","unicode":"U+1F46A","name":"family"},"couple":{"shortname":"couple","emoji":"\ud83d\udc6b","unicode":"U+1F46B","name":"man and woman holding hands"},"two_men_holding_hands":{"shortname":"two_men_holding_hands","emoji":"\ud83d\udc6c","unicode":"U+1F46C","name":"two men holding hands"},"two_women_holding_hands":{"shortname":"two_women_holding_hands","emoji":"\ud83d\udc6d","unicode":"U+1F46D","name":"two women holding hands"},"cop":{"shortname":"cop","emoji":"\ud83d\udc6e","unicode":"U+1F46E","name":"police officer"},"dancers":{"shortname":"dancers","emoji":"\ud83d\udc6f","unicode":"U+1F46F","name":"woman with bunny ears"},"bride_with_veil":{"shortname":"bride_with_veil","emoji":"\ud83d\udc70","unicode":"U+1F470","name":"bride with veil"},"person_with_blond_hair":{"shortname":"person_with_blond_hair","emoji":"\ud83d\udc71","unicode":"U+1F471","name":"person with blond hair"},"man_with_gua_pi_mao":{"shortname":"man_with_gua_pi_mao","emoji":"\ud83d\udc72","unicode":"U+1F472","name":"man with gua pi mao"},"man_with_turban":{"shortname":"man_with_turban","emoji":"\ud83d\udc73","unicode":"U+1F473","name":"man with turban"},"older_man":{"shortname":"older_man","emoji":"\ud83d\udc74","unicode":"U+1F474","name":"older man"},"older_woman":{"shortname":"older_woman","emoji":"\ud83d\udc75","unicode":"U+1F475","name":"older woman"},"baby":{"shortname":"baby","emoji":"\ud83d\udc76","unicode":"U+1F476","name":"baby"},"construction_worker":{"shortname":"construction_worker","emoji":"\ud83d\udc77","unicode":"U+1F477","name":"construction worker"},"princess":{"shortname":"princess","emoji":"\ud83d\udc78","unicode":"U+1F478","name":"princess"},"japanese_ogre":{"shortname":"japanese_ogre","emoji":"\ud83d\udc79","unicode":"U+1F479","name":"japanese ogre"},"japanese_goblin":{"shortname":"japanese_goblin","emoji":"\ud83d\udc7a","unicode":"U+1F47A","name":"japanese goblin"},"ghost":{"shortname":"ghost","emoji":"\ud83d\udc7b","unicode":"U+1F47B","name":"ghost"},"angel":{"shortname":"angel","emoji":"\ud83d\udc7c","unicode":"U+1F47C","name":"baby angel"},"alien":{"shortname":"alien","emoji":"\ud83d\udc7d","unicode":"U+1F47D","name":"extraterrestrial alien"},"space_invader":{"shortname":"space_invader","emoji":"\ud83d\udc7e","unicode":"U+1F47E","name":"alien monster"},"imp":{"shortname":"imp","emoji":"\ud83d\udc7f","unicode":"U+1F47F","name":"imp"},"skull":{"shortname":"skull","emoji":"\ud83d\udc80","unicode":"U+1F480","name":"skull"},"information_desk_person":{"shortname":"information_desk_person","emoji":"\ud83d\udc81","unicode":"U+1F481","name":"information desk person"},"guardsman":{"shortname":"guardsman","emoji":"\ud83d\udc82","unicode":"U+1F482","name":"guardsman"},"dancer":{"shortname":"dancer","emoji":"\ud83d\udc83","unicode":"U+1F483","name":"dancer"},"lipstick":{"shortname":"lipstick","emoji":"\ud83d\udc84","unicode":"U+1F484","name":"lipstick"},"nail_care":{"shortname":"nail_care","emoji":"\ud83d\udc85","unicode":"U+1F485","name":"nail polish"},"massage":{"shortname":"massage","emoji":"\ud83d\udc86","unicode":"U+1F486","name":"face massage"},"haircut":{"shortname":"haircut","emoji":"\ud83d\udc87","unicode":"U+1F487","name":"haircut"},"barber":{"shortname":"barber","emoji":"\ud83d\udc88","unicode":"U+1F488","name":"barber pole"},"syringe":{"shortname":"syringe","emoji":"\ud83d\udc89","unicode":"U+1F489","name":"syringe"},"pill":{"shortname":"pill","emoji":"\ud83d\udc8a","unicode":"U+1F48A","name":"pill"},"kiss":{"shortname":"kiss","emoji":"\ud83d\udc8b","unicode":"U+1F48B","name":"kiss mark"},"love_letter":{"shortname":"love_letter","emoji":"\ud83d\udc8c","unicode":"U+1F48C","name":"love letter"},"ring":{"shortname":"ring","emoji":"\ud83d\udc8d","unicode":"U+1F48D","name":"ring"},"gem":{"shortname":"gem","emoji":"\ud83d\udc8e","unicode":"U+1F48E","name":"gem stone"},"couplekiss":{"shortname":"couplekiss","emoji":"\ud83d\udc8f","unicode":"U+1F48F","name":"kiss"},"bouquet":{"shortname":"bouquet","emoji":"\ud83d\udc90","unicode":"U+1F490","name":"bouquet"},"couple_with_heart":{"shortname":"couple_with_heart","emoji":"\ud83d\udc91","unicode":"U+1F491","name":"couple with heart"},"wedding":{"shortname":"wedding","emoji":"\ud83d\udc92","unicode":"U+1F492","name":"wedding"},"heartbeat":{"shortname":"heartbeat","emoji":"\ud83d\udc93","unicode":"U+1F493","name":"beating heart"},"broken_heart":{"shortname":"broken_heart","emoji":"\ud83d\udc94","unicode":"U+1F494","name":"broken heart"},"two_hearts":{"shortname":"two_hearts","emoji":"\ud83d\udc95","unicode":"U+1F495","name":"two hearts"},"sparkling_heart":{"shortname":"sparkling_heart","emoji":"\ud83d\udc96","unicode":"U+1F496","name":"sparkling heart"},"heartpulse":{"shortname":"heartpulse","emoji":"\ud83d\udc97","unicode":"U+1F497","name":"growing heart"},"cupid":{"shortname":"cupid","emoji":"\ud83d\udc98","unicode":"U+1F498","name":"heart with arrow"},"blue_heart":{"shortname":"blue_heart","emoji":"\ud83d\udc99","unicode":"U+1F499","name":"blue heart"},"green_heart":{"shortname":"green_heart","emoji":"\ud83d\udc9a","unicode":"U+1F49A","name":"green heart"},"yellow_heart":{"shortname":"yellow_heart","emoji":"\ud83d\udc9b","unicode":"U+1F49B","name":"yellow heart"},"purple_heart":{"shortname":"purple_heart","emoji":"\ud83d\udc9c","unicode":"U+1F49C","name":"purple heart"},"gift_heart":{"shortname":"gift_heart","emoji":"\ud83d\udc9d","unicode":"U+1F49D","name":"heart with ribbon"},"revolving_hearts":{"shortname":"revolving_hearts","emoji":"\ud83d\udc9e","unicode":"U+1F49E","name":"revolving hearts"},"heart_decoration":{"shortname":"heart_decoration","emoji":"\ud83d\udc9f","unicode":"U+1F49F","name":"heart decoration"},"diamond_shape_with_a_dot_inside":{"shortname":"diamond_shape_with_a_dot_inside","emoji":"\ud83d\udca0","unicode":"U+1F4A0","name":"diamond shape with a dot inside"},"bulb":{"shortname":"bulb","emoji":"\ud83d\udca1","unicode":"U+1F4A1","name":"electric light bulb"},"anger":{"shortname":"anger","emoji":"\ud83d\udca2","unicode":"U+1F4A2","name":"anger symbol"},"bomb":{"shortname":"bomb","emoji":"\ud83d\udca3","unicode":"U+1F4A3","name":"bomb"},"zzz":{"shortname":"zzz","emoji":"\ud83d\udca4","unicode":"U+1F4A4","name":"sleeping symbol"},"boom":{"shortname":"boom","emoji":"\ud83d\udca5","unicode":"U+1F4A5","name":"collision symbol"},"sweat_drops":{"shortname":"sweat_drops","emoji":"\ud83d\udca6","unicode":"U+1F4A6","name":"splashing sweat symbol"},"droplet":{"shortname":"droplet","emoji":"\ud83d\udca7","unicode":"U+1F4A7","name":"droplet"},"dash":{"shortname":"dash","emoji":"\ud83d\udca8","unicode":"U+1F4A8","name":"dash symbol"},"hankey":{"shortname":"hankey","emoji":"\ud83d\udca9","unicode":"U+1F4A9","name":"pile of poo"},"muscle":{"shortname":"muscle","emoji":"\ud83d\udcaa","unicode":"U+1F4AA","name":"flexed biceps"},"dizzy":{"shortname":"dizzy","emoji":"\ud83d\udcab","unicode":"U+1F4AB","name":"dizzy symbol"},"speech_balloon":{"shortname":"speech_balloon","emoji":"\ud83d\udcac","unicode":"U+1F4AC","name":"speech balloon"},"thought_balloon":{"shortname":"thought_balloon","emoji":"\ud83d\udcad","unicode":"U+1F4AD","name":"thought balloon"},"white_flower":{"shortname":"white_flower","emoji":"\ud83d\udcae","unicode":"U+1F4AE","name":"white flower"},"100":{"shortname":"100","emoji":"\ud83d\udcaf","unicode":"U+1F4AF","name":"hundred points symbol"},"moneybag":{"shortname":"moneybag","emoji":"\ud83d\udcb0","unicode":"U+1F4B0","name":"money bag"},"currency_exchange":{"shortname":"currency_exchange","emoji":"\ud83d\udcb1","unicode":"U+1F4B1","name":"currency exchange"},"heavy_dollar_sign":{"shortname":"heavy_dollar_sign","emoji":"\ud83d\udcb2","unicode":"U+1F4B2","name":"heavy dollar sign"},"credit_card":{"shortname":"credit_card","emoji":"\ud83d\udcb3","unicode":"U+1F4B3","name":"credit card"},"yen":{"shortname":"yen","emoji":"\ud83d\udcb4","unicode":"U+1F4B4","name":"banknote with yen sign"},"dollar":{"shortname":"dollar","emoji":"\ud83d\udcb5","unicode":"U+1F4B5","name":"banknote with dollar sign"},"euro":{"shortname":"euro","emoji":"\ud83d\udcb6","unicode":"U+1F4B6","name":"banknote with euro sign"},"pound":{"shortname":"pound","emoji":"\ud83d\udcb7","unicode":"U+1F4B7","name":"banknote with pound sign"},"money_with_wings":{"shortname":"money_with_wings","emoji":"\ud83d\udcb8","unicode":"U+1F4B8","name":"money with wings"},"chart":{"shortname":"chart","emoji":"\ud83d\udcb9","unicode":"U+1F4B9","name":"chart with upwards trend and yen sign"},"seat":{"shortname":"seat","emoji":"\ud83d\udcba","unicode":"U+1F4BA","name":"seat"},"computer":{"shortname":"computer","emoji":"\ud83d\udcbb","unicode":"U+1F4BB","name":"personal computer"},"briefcase":{"shortname":"briefcase","emoji":"\ud83d\udcbc","unicode":"U+1F4BC","name":"briefcase"},"minidisc":{"shortname":"minidisc","emoji":"\ud83d\udcbd","unicode":"U+1F4BD","name":"minidisc"},"floppy_disk":{"shortname":"floppy_disk","emoji":"\ud83d\udcbe","unicode":"U+1F4BE","name":"floppy disk"},"cd":{"shortname":"cd","emoji":"\ud83d\udcbf","unicode":"U+1F4BF","name":"optical disc"},"dvd":{"shortname":"dvd","emoji":"\ud83d\udcc0","unicode":"U+1F4C0","name":"dvd"},"file_folder":{"shortname":"file_folder","emoji":"\ud83d\udcc1","unicode":"U+1F4C1","name":"file folder"},"open_file_folder":{"shortname":"open_file_folder","emoji":"\ud83d\udcc2","unicode":"U+1F4C2","name":"open file folder"},"page_with_curl":{"shortname":"page_with_curl","emoji":"\ud83d\udcc3","unicode":"U+1F4C3","name":"page with curl"},"page_facing_up":{"shortname":"page_facing_up","emoji":"\ud83d\udcc4","unicode":"U+1F4C4","name":"page facing up"},"date":{"shortname":"date","emoji":"\ud83d\udcc5","unicode":"U+1F4C5","name":"calendar"},"calendar":{"shortname":"calendar","emoji":"\ud83d\udcc6","unicode":"U+1F4C6","name":"tear-off calendar"},"card_index":{"shortname":"card_index","emoji":"\ud83d\udcc7","unicode":"U+1F4C7","name":"card index"},"chart_with_upwards_trend":{"shortname":"chart_with_upwards_trend","emoji":"\ud83d\udcc8","unicode":"U+1F4C8","name":"chart with upwards trend"},"chart_with_downwards_trend":{"shortname":"chart_with_downwards_trend","emoji":"\ud83d\udcc9","unicode":"U+1F4C9","name":"chart with downwards trend"},"bar_chart":{"shortname":"bar_chart","emoji":"\ud83d\udcca","unicode":"U+1F4CA","name":"bar chart"},"clipboard":{"shortname":"clipboard","emoji":"\ud83d\udccb","unicode":"U+1F4CB","name":"clipboard"},"pushpin":{"shortname":"pushpin","emoji":"\ud83d\udccc","unicode":"U+1F4CC","name":"pushpin"},"round_pushpin":{"shortname":"round_pushpin","emoji":"\ud83d\udccd","unicode":"U+1F4CD","name":"round pushpin"},"paperclip":{"shortname":"paperclip","emoji":"\ud83d\udcce","unicode":"U+1F4CE","name":"paperclip"},"straight_ruler":{"shortname":"straight_ruler","emoji":"\ud83d\udccf","unicode":"U+1F4CF","name":"straight ruler"},"triangular_ruler":{"shortname":"triangular_ruler","emoji":"\ud83d\udcd0","unicode":"U+1F4D0","name":"triangular ruler"},"bookmark_tabs":{"shortname":"bookmark_tabs","emoji":"\ud83d\udcd1","unicode":"U+1F4D1","name":"bookmark tabs"},"ledger":{"shortname":"ledger","emoji":"\ud83d\udcd2","unicode":"U+1F4D2","name":"ledger"},"notebook":{"shortname":"notebook","emoji":"\ud83d\udcd3","unicode":"U+1F4D3","name":"notebook"},"notebook_with_decorative_cover":{"shortname":"notebook_with_decorative_cover","emoji":"\ud83d\udcd4","unicode":"U+1F4D4","name":"notebook with decorative cover"},"closed_book":{"shortname":"closed_book","emoji":"\ud83d\udcd5","unicode":"U+1F4D5","name":"closed book"},"book":{"shortname":"book","emoji":"\ud83d\udcd6","unicode":"U+1F4D6","name":"open book"},"green_book":{"shortname":"green_book","emoji":"\ud83d\udcd7","unicode":"U+1F4D7","name":"green book"},"blue_book":{"shortname":"blue_book","emoji":"\ud83d\udcd8","unicode":"U+1F4D8","name":"blue book"},"orange_book":{"shortname":"orange_book","emoji":"\ud83d\udcd9","unicode":"U+1F4D9","name":"orange book"},"books":{"shortname":"books","emoji":"\ud83d\udcda","unicode":"U+1F4DA","name":"books"},"name_badge":{"shortname":"name_badge","emoji":"\ud83d\udcdb","unicode":"U+1F4DB","name":"name badge"},"scroll":{"shortname":"scroll","emoji":"\ud83d\udcdc","unicode":"U+1F4DC","name":"scroll"},"memo":{"shortname":"memo","emoji":"\ud83d\udcdd","unicode":"U+1F4DD","name":"memo"},"telephone_receiver":{"shortname":"telephone_receiver","emoji":"\ud83d\udcde","unicode":"U+1F4DE","name":"telephone receiver"},"pager":{"shortname":"pager","emoji":"\ud83d\udcdf","unicode":"U+1F4DF","name":"pager"},"fax":{"shortname":"fax","emoji":"\ud83d\udce0","unicode":"U+1F4E0","name":"fax machine"},"satellite":{"shortname":"satellite","emoji":"\ud83d\udce1","unicode":"U+1F4E1","name":"satellite antenna"},"loudspeaker":{"shortname":"loudspeaker","emoji":"\ud83d\udce2","unicode":"U+1F4E2","name":"public address loudspeaker"},"mega":{"shortname":"mega","emoji":"\ud83d\udce3","unicode":"U+1F4E3","name":"cheering megaphone"},"outbox_tray":{"shortname":"outbox_tray","emoji":"\ud83d\udce4","unicode":"U+1F4E4","name":"outbox tray"},"inbox_tray":{"shortname":"inbox_tray","emoji":"\ud83d\udce5","unicode":"U+1F4E5","name":"inbox tray"},"package":{"shortname":"package","emoji":"\ud83d\udce6","unicode":"U+1F4E6","name":"package"},"e-mail":{"shortname":"e-mail","emoji":"\ud83d\udce7","unicode":"U+1F4E7","name":"e-mail symbol"},"incoming_envelope":{"shortname":"incoming_envelope","emoji":"\ud83d\udce8","unicode":"U+1F4E8","name":"incoming envelope"},"envelope_with_arrow":{"shortname":"envelope_with_arrow","emoji":"\ud83d\udce9","unicode":"U+1F4E9","name":"envelope with downwards arrow above"},"mailbox_closed":{"shortname":"mailbox_closed","emoji":"\ud83d\udcea","unicode":"U+1F4EA","name":"closed mailbox with lowered flag"},"mailbox":{"shortname":"mailbox","emoji":"\ud83d\udceb","unicode":"U+1F4EB","name":"closed mailbox with raised flag"},"mailbox_with_mail":{"shortname":"mailbox_with_mail","emoji":"\ud83d\udcec","unicode":"U+1F4EC","name":"open mailbox with raised flag"},"mailbox_with_no_mail":{"shortname":"mailbox_with_no_mail","emoji":"\ud83d\udced","unicode":"U+1F4ED","name":"open mailbox with lowered flag"},"postbox":{"shortname":"postbox","emoji":"\ud83d\udcee","unicode":"U+1F4EE","name":"postbox"},"postal_horn":{"shortname":"postal_horn","emoji":"\ud83d\udcef","unicode":"U+1F4EF","name":"postal horn"},"newspaper":{"shortname":"newspaper","emoji":"\ud83d\udcf0","unicode":"U+1F4F0","name":"newspaper"},"iphone":{"shortname":"iphone","emoji":"\ud83d\udcf1","unicode":"U+1F4F1","name":"mobile phone"},"calling":{"shortname":"calling","emoji":"\ud83d\udcf2","unicode":"U+1F4F2","name":"mobile phone with rightwards arrow at left"},"vibration_mode":{"shortname":"vibration_mode","emoji":"\ud83d\udcf3","unicode":"U+1F4F3","name":"vibration mode"},"mobile_phone_off":{"shortname":"mobile_phone_off","emoji":"\ud83d\udcf4","unicode":"U+1F4F4","name":"mobile phone off"},"no_mobile_phones":{"shortname":"no_mobile_phones","emoji":"\ud83d\udcf5","unicode":"U+1F4F5","name":"no mobile phones"},"signal_strength":{"shortname":"signal_strength","emoji":"\ud83d\udcf6","unicode":"U+1F4F6","name":"antenna with bars"},"camera":{"shortname":"camera","emoji":"\ud83d\udcf7","unicode":"U+1F4F7","name":"camera"},"video_camera":{"shortname":"video_camera","emoji":"\ud83d\udcf9","unicode":"U+1F4F9","name":"video camera"},"tv":{"shortname":"tv","emoji":"\ud83d\udcfa","unicode":"U+1F4FA","name":"television"},"radio":{"shortname":"radio","emoji":"\ud83d\udcfb","unicode":"U+1F4FB","name":"radio"},"vhs":{"shortname":"vhs","emoji":"\ud83d\udcfc","unicode":"U+1F4FC","name":"videocassette"},"twisted_rightwards_arrows":{"shortname":"twisted_rightwards_arrows","emoji":"\ud83d\udd00","unicode":"U+1F500","name":"twisted rightwards arrows"},"repeat":{"shortname":"repeat","emoji":"\ud83d\udd01","unicode":"U+1F501","name":"clockwise rightwards and leftwards open circle arrows"},"repeat_one":{"shortname":"repeat_one","emoji":"\ud83d\udd02","unicode":"U+1F502","name":"clockwise rightwards and leftwards open circle arrows with circled one overlay"},"arrows_clockwise":{"shortname":"arrows_clockwise","emoji":"\ud83d\udd03","unicode":"U+1F503","name":"clockwise downwards and upwards open circle arrows"},"arrows_counterclockwise":{"shortname":"arrows_counterclockwise","emoji":"\ud83d\udd04","unicode":"U+1F504","name":"anticlockwise downwards and upwards open circle arrows"},"low_brightness":{"shortname":"low_brightness","emoji":"\ud83d\udd05","unicode":"U+1F505","name":"low brightness symbol"},"high_brightness":{"shortname":"high_brightness","emoji":"\ud83d\udd06","unicode":"U+1F506","name":"high brightness symbol"},"mute":{"shortname":"mute","emoji":"\ud83d\udd07","unicode":"U+1F507","name":"speaker with cancellation stroke"},"speaker":{"shortname":"speaker","emoji":null,"unicode":"U+1F508","name":"speaker"},"sound":{"shortname":"sound","emoji":"\ud83d\udd09","unicode":"U+1F509","name":"speaker with one sound wave"},"loud_sound":{"shortname":"loud_sound","emoji":"\ud83d\udd0a","unicode":"U+1F50A","name":"speaker with three sound waves"},"battery":{"shortname":"battery","emoji":"\ud83d\udd0b","unicode":"U+1F50B","name":"battery"},"electric_plug":{"shortname":"electric_plug","emoji":"\ud83d\udd0c","unicode":"U+1F50C","name":"electric plug"},"mag":{"shortname":"mag","emoji":"\ud83d\udd0d","unicode":"U+1F50D","name":"left-pointing magnifying glass"},"mag_right":{"shortname":"mag_right","emoji":"\ud83d\udd0e","unicode":"U+1F50E","name":"right-pointing magnifying glass"},"lock_with_ink_pen":{"shortname":"lock_with_ink_pen","emoji":"\ud83d\udd0f","unicode":"U+1F50F","name":"lock with ink pen"},"closed_lock_with_key":{"shortname":"closed_lock_with_key","emoji":"\ud83d\udd10","unicode":"U+1F510","name":"closed lock with key"},"key":{"shortname":"key","emoji":"\ud83d\udd11","unicode":"U+1F511","name":"key"},"lock":{"shortname":"lock","emoji":"\ud83d\udd12","unicode":"U+1F512","name":"lock"},"unlock":{"shortname":"unlock","emoji":"\ud83d\udd13","unicode":"U+1F513","name":"open lock"},"bell":{"shortname":"bell","emoji":"\ud83d\udd14","unicode":"U+1F514","name":"bell"},"no_bell":{"shortname":"no_bell","emoji":"\ud83d\udd15","unicode":"U+1F515","name":"bell with cancellation stroke"},"bookmark":{"shortname":"bookmark","emoji":"\ud83d\udd16","unicode":"U+1F516","name":"bookmark"},"link":{"shortname":"link","emoji":"\ud83d\udd17","unicode":"U+1F517","name":"link symbol"},"radio_button":{"shortname":"radio_button","emoji":"\ud83d\udd18","unicode":"U+1F518","name":"radio button"},"back":{"shortname":"back","emoji":"\ud83d\udd19","unicode":"U+1F519","name":"back with leftwards arrow above"},"end":{"shortname":"end","emoji":"\ud83d\udd1a","unicode":"U+1F51A","name":"end with leftwards arrow above"},"on":{"shortname":"on","emoji":"\ud83d\udd1b","unicode":"U+1F51B","name":"on with exclamation mark with left right arrow above"},"soon":{"shortname":"soon","emoji":"\ud83d\udd1c","unicode":"U+1F51C","name":"soon with rightwards arrow above"},"top":{"shortname":"top","emoji":"\ud83d\udd1d","unicode":"U+1F51D","name":"top with upwards arrow above"},"underage":{"shortname":"underage","emoji":"\ud83d\udd1e","unicode":"U+1F51E","name":"no one under eighteen symbol"},"keycap_ten":{"shortname":"keycap_ten","emoji":"\ud83d\udd1f","unicode":"U+1F51F","name":"keycap ten"},"capital_abcd":{"shortname":"capital_abcd","emoji":"\ud83d\udd20","unicode":"U+1F520","name":"input symbol for latin capital letters"},"abcd":{"shortname":"abcd","emoji":"\ud83d\udd21","unicode":"U+1F521","name":"input symbol for latin small letters"},"1234":{"shortname":"1234","emoji":"\ud83d\udd22","unicode":"U+1F522","name":"input symbol for numbers"},"symbols":{"shortname":"symbols","emoji":"\ud83d\udd23","unicode":"U+1F523","name":"input symbol for symbols"},"abc":{"shortname":"abc","emoji":"\ud83d\udd24","unicode":"U+1F524","name":"input symbol for latin letters"},"fire":{"shortname":"fire","emoji":"\ud83d\udd25","unicode":"U+1F525","name":"fire"},"flashlight":{"shortname":"flashlight","emoji":"\ud83d\udd26","unicode":"U+1F526","name":"electric torch"},"wrench":{"shortname":"wrench","emoji":"\ud83d\udd27","unicode":"U+1F527","name":"wrench"},"hammer":{"shortname":"hammer","emoji":"\ud83d\udd28","unicode":"U+1F528","name":"hammer"},"nut_and_bolt":{"shortname":"nut_and_bolt","emoji":"\ud83d\udd29","unicode":"U+1F529","name":"nut and bolt"},"hocho":{"shortname":"hocho","emoji":"\ud83d\udd2a","unicode":"U+1F52A","name":"hocho"},"gun":{"shortname":"gun","emoji":"\ud83d\udd2b","unicode":"U+1F52B","name":"pistol"},"microscope":{"shortname":"microscope","emoji":"\ud83d\udd2c","unicode":"U+1F52C","name":"microscope"},"telescope":{"shortname":"telescope","emoji":"\ud83d\udd2d","unicode":"U+1F52D","name":"telescope"},"crystal_ball":{"shortname":"crystal_ball","emoji":"\ud83d\udd2e","unicode":"U+1F52E","name":"crystal ball"},"six_pointed_star":{"shortname":"six_pointed_star","emoji":"\ud83d\udd2f","unicode":"U+1F52F","name":"six pointed star with middle dot"},"beginner":{"shortname":"beginner","emoji":"\ud83d\udd30","unicode":"U+1F530","name":"japanese symbol for beginner"},"trident":{"shortname":"trident","emoji":"\ud83d\udd31","unicode":"U+1F531","name":"trident emblem"},"black_square_button":{"shortname":"black_square_button","emoji":"\ud83d\udd32","unicode":"U+1F532","name":"black square button"},"white_square_button":{"shortname":"white_square_button","emoji":"\ud83d\udd33","unicode":"U+1F533","name":"white square button"},"red_circle":{"shortname":"red_circle","emoji":"\ud83d\udd34","unicode":"U+1F534","name":"large red circle"},"large_blue_circle":{"shortname":"large_blue_circle","emoji":"\ud83d\udd35","unicode":"U+1F535","name":"large blue circle"},"large_orange_diamond":{"shortname":"large_orange_diamond","emoji":"\ud83d\udd36","unicode":"U+1F536","name":"large orange diamond"},"large_blue_diamond":{"shortname":"large_blue_diamond","emoji":"\ud83d\udd37","unicode":"U+1F537","name":"large blue diamond"},"small_orange_diamond":{"shortname":"small_orange_diamond","emoji":"\ud83d\udd38","unicode":"U+1F538","name":"small orange diamond"},"small_blue_diamond":{"shortname":"small_blue_diamond","emoji":"\ud83d\udd39","unicode":"U+1F539","name":"small blue diamond"},"small_red_triangle":{"shortname":"small_red_triangle","emoji":"\ud83d\udd3a","unicode":"U+1F53A","name":"up-pointing red triangle"},"small_red_triangle_down":{"shortname":"small_red_triangle_down","emoji":"\ud83d\udd3b","unicode":"U+1F53B","name":"down-pointing red triangle"},"arrow_up_small":{"shortname":"arrow_up_small","emoji":"\ud83d\udd3c","unicode":"U+1F53C","name":"up-pointing small red triangle"},"arrow_down_small":{"shortname":"arrow_down_small","emoji":"\ud83d\udd3d","unicode":"U+1F53D","name":"down-pointing small red triangle"},"clock1":{"shortname":"clock1","emoji":"\ud83d\udd50","unicode":"U+1F550","name":"clock face one oclock"},"clock2":{"shortname":"clock2","emoji":"\ud83d\udd51","unicode":"U+1F551","name":"clock face two oclock"},"clock3":{"shortname":"clock3","emoji":"\ud83d\udd52","unicode":"U+1F552","name":"clock face three oclock"},"clock4":{"shortname":"clock4","emoji":"\ud83d\udd53","unicode":"U+1F553","name":"clock face four oclock"},"clock5":{"shortname":"clock5","emoji":"\ud83d\udd54","unicode":"U+1F554","name":"clock face five oclock"},"clock6":{"shortname":"clock6","emoji":"\ud83d\udd55","unicode":"U+1F555","name":"clock face six oclock"},"clock7":{"shortname":"clock7","emoji":"\ud83d\udd56","unicode":"U+1F556","name":"clock face seven oclock"},"clock8":{"shortname":"clock8","emoji":"\ud83d\udd57","unicode":"U+1F557","name":"clock face eight oclock"},"clock9":{"shortname":"clock9","emoji":"\ud83d\udd58","unicode":"U+1F558","name":"clock face nine oclock"},"clock10":{"shortname":"clock10","emoji":"\ud83d\udd59","unicode":"U+1F559","name":"clock face ten oclock"},"clock11":{"shortname":"clock11","emoji":"\ud83d\udd5a","unicode":"U+1F55A","name":"clock face eleven oclock"},"clock12":{"shortname":"clock12","emoji":"\ud83d\udd5b","unicode":"U+1F55B","name":"clock face twelve oclock"},"clock130":{"shortname":"clock130","emoji":"\ud83d\udd5c","unicode":"U+1F55C","name":"clock face one-thirty"},"clock230":{"shortname":"clock230","emoji":"\ud83d\udd5d","unicode":"U+1F55D","name":"clock face two-thirty"},"clock330":{"shortname":"clock330","emoji":"\ud83d\udd5e","unicode":"U+1F55E","name":"clock face three-thirty"},"clock430":{"shortname":"clock430","emoji":"\ud83d\udd5f","unicode":"U+1F55F","name":"clock face four-thirty"},"clock530":{"shortname":"clock530","emoji":"\ud83d\udd60","unicode":"U+1F560","name":"clock face five-thirty"},"clock630":{"shortname":"clock630","emoji":"\ud83d\udd61","unicode":"U+1F561","name":"clock face six-thirty"},"clock730":{"shortname":"clock730","emoji":"\ud83d\udd62","unicode":"U+1F562","name":"clock face seven-thirty"},"clock830":{"shortname":"clock830","emoji":"\ud83d\udd63","unicode":"U+1F563","name":"clock face eight-thirty"},"clock930":{"shortname":"clock930","emoji":"\ud83d\udd64","unicode":"U+1F564","name":"clock face nine-thirty"},"clock1030":{"shortname":"clock1030","emoji":"\ud83d\udd65","unicode":"U+1F565","name":"clock face ten-thirty"},"clock1130":{"shortname":"clock1130","emoji":"\ud83d\udd66","unicode":"U+1F566","name":"clock face eleven-thirty"},"clock1230":{"shortname":"clock1230","emoji":"\ud83d\udd67","unicode":"U+1F567","name":"clock face twelve-thirty"},"mount_fuji":{"shortname":"mount_fuji","emoji":"\ud83d\uddfb","unicode":"U+1F5FB","name":"mount fuji"},"tokyo_tower":{"shortname":"tokyo_tower","emoji":"\ud83d\uddfc","unicode":"U+1F5FC","name":"tokyo tower"},"statue_of_liberty":{"shortname":"statue_of_liberty","emoji":"\ud83d\uddfd","unicode":"U+1F5FD","name":"statue of liberty"},"japan":{"shortname":"japan","emoji":"\ud83d\uddfe","unicode":"U+1F5FE","name":"silhouette of japan"},"moyai":{"shortname":"moyai","emoji":"\ud83d\uddff","unicode":"U+1F5FF","name":"moyai"},"grinning":{"shortname":"grinning","emoji":"\ud83d\ude00","unicode":"U+1F600","name":"grinning face"},"grin":{"shortname":"grin","emoji":"\ud83d\ude01","unicode":"U+1F601","name":"grinning face with smiling eyes"},"joy":{"shortname":"joy","emoji":"\ud83d\ude02","unicode":"U+1F602","name":"face with tears of joy"},"smiley":{"shortname":"smiley","emoji":"\ud83d\ude03","unicode":"U+1F603","name":"smiling face with open mouth"},"smile":{"shortname":"smile","emoji":"\ud83d\ude04","unicode":"U+1F604","name":"smiling face with open mouth and smiling eyes"},"sweat_smile":{"shortname":"sweat_smile","emoji":"\ud83d\ude05","unicode":"U+1F605","name":"smiling face with open mouth and cold sweat"},"laughing":{"shortname":"laughing","emoji":"\ud83d\ude06","unicode":"U+1F606","name":"smiling face with open mouth and tightly-closed eyes"},"innocent":{"shortname":"innocent","emoji":"\ud83d\ude07","unicode":"U+1F607","name":"smiling face with halo"},"smiling_imp":{"shortname":"smiling_imp","emoji":"\ud83d\ude08","unicode":"U+1F608","name":"smiling face with horns"},"wink":{"shortname":"wink","emoji":"\ud83d\ude09","unicode":"U+1F609","name":"winking face"},"blush":{"shortname":"blush","emoji":"\ud83d\ude0a","unicode":"U+1F60A","name":"smiling face with smiling eyes"},"yum":{"shortname":"yum","emoji":"\ud83d\ude0b","unicode":"U+1F60B","name":"face savouring delicious food"},"relieved":{"shortname":"relieved","emoji":"\ud83d\ude0c","unicode":"U+1F60C","name":"relieved face"},"heart_eyes":{"shortname":"heart_eyes","emoji":"\ud83d\ude0d","unicode":"U+1F60D","name":"smiling face with heart-shaped eyes"},"sunglasses":{"shortname":"sunglasses","emoji":"\ud83d\ude0e","unicode":"U+1F60E","name":"smiling face with sunglasses"},"smirk":{"shortname":"smirk","emoji":"\ud83d\ude0f","unicode":"U+1F60F","name":"smirking face"},"neutral_face":{"shortname":"neutral_face","emoji":"\ud83d\ude10","unicode":"U+1F610","name":"neutral face"},"expressionless":{"shortname":"expressionless","emoji":"\ud83d\ude11","unicode":"U+1F611","name":"expressionless face"},"unamused":{"shortname":"unamused","emoji":"\ud83d\ude12","unicode":"U+1F612","name":"unamused face"},"sweat":{"shortname":"sweat","emoji":"\ud83d\ude13","unicode":"U+1F613","name":"face with cold sweat"},"pensive":{"shortname":"pensive","emoji":"\ud83d\ude14","unicode":"U+1F614","name":"pensive face"},"confused":{"shortname":"confused","emoji":"\ud83d\ude15","unicode":"U+1F615","name":"confused face"},"confounded":{"shortname":"confounded","emoji":"\ud83d\ude16","unicode":"U+1F616","name":"confounded face"},"kissing":{"shortname":"kissing","emoji":"\ud83d\ude17","unicode":"U+1F617","name":"kissing face"},"kissing_heart":{"shortname":"kissing_heart","emoji":"\ud83d\ude18","unicode":"U+1F618","name":"face throwing a kiss"},"kissing_smiling_eyes":{"shortname":"kissing_smiling_eyes","emoji":"\ud83d\ude19","unicode":"U+1F619","name":"kissing face with smiling eyes"},"kissing_closed_eyes":{"shortname":"kissing_closed_eyes","emoji":"\ud83d\ude1a","unicode":"U+1F61A","name":"kissing face with closed eyes"},"stuck_out_tongue":{"shortname":"stuck_out_tongue","emoji":"\ud83d\ude1b","unicode":"U+1F61B","name":"face with stuck-out tongue"},"stuck_out_tongue_winking_eye":{"shortname":"stuck_out_tongue_winking_eye","emoji":"\ud83d\ude1c","unicode":"U+1F61C","name":"face with stuck-out tongue and winking eye"},"stuck_out_tongue_closed_eyes":{"shortname":"stuck_out_tongue_closed_eyes","emoji":"\ud83d\ude1d","unicode":"U+1F61D","name":"face with stuck-out tongue and tightly-closed eyes"},"disappointed":{"shortname":"disappointed","emoji":"\ud83d\ude1e","unicode":"U+1F61E","name":"disappointed face"},"worried":{"shortname":"worried","emoji":"\ud83d\ude1f","unicode":"U+1F61F","name":"worried face"},"angry":{"shortname":"angry","emoji":"\ud83d\ude20","unicode":"U+1F620","name":"angry face"},"rage":{"shortname":"rage","emoji":"\ud83d\ude21","unicode":"U+1F621","name":"pouting face"},"cry":{"shortname":"cry","emoji":"\ud83d\ude22","unicode":"U+1F622","name":"crying face"},"persevere":{"shortname":"persevere","emoji":"\ud83d\ude23","unicode":"U+1F623","name":"persevering face"},"triumph":{"shortname":"triumph","emoji":"\ud83d\ude24","unicode":"U+1F624","name":"face with look of triumph"},"disappointed_relieved":{"shortname":"disappointed_relieved","emoji":"\ud83d\ude25","unicode":"U+1F625","name":"disappointed but relieved face"},"frowning":{"shortname":"frowning","emoji":"\ud83d\ude26","unicode":"U+1F626","name":"frowning face with open mouth"},"anguished":{"shortname":"anguished","emoji":"\ud83d\ude27","unicode":"U+1F627","name":"anguished face"},"fearful":{"shortname":"fearful","emoji":"\ud83d\ude28","unicode":"U+1F628","name":"fearful face"},"weary":{"shortname":"weary","emoji":"\ud83d\ude29","unicode":"U+1F629","name":"weary face"},"sleepy":{"shortname":"sleepy","emoji":"\ud83d\ude2a","unicode":"U+1F62A","name":"sleepy face"},"tired_face":{"shortname":"tired_face","emoji":"\ud83d\ude2b","unicode":"U+1F62B","name":"tired face"},"grimacing":{"shortname":"grimacing","emoji":"\ud83d\ude2c","unicode":"U+1F62C","name":"grimacing face"},"sob":{"shortname":"sob","emoji":"\ud83d\ude2d","unicode":"U+1F62D","name":"loudly crying face"},"open_mouth":{"shortname":"open_mouth","emoji":"\ud83d\ude2e","unicode":"U+1F62E","name":"face with open mouth"},"hushed":{"shortname":"hushed","emoji":"\ud83d\ude2f","unicode":"U+1F62F","name":"hushed face"},"cold_sweat":{"shortname":"cold_sweat","emoji":"\ud83d\ude30","unicode":"U+1F630","name":"face with open mouth and cold sweat"},"scream":{"shortname":"scream","emoji":"\ud83d\ude31","unicode":"U+1F631","name":"face screaming in fear"},"astonished":{"shortname":"astonished","emoji":"\ud83d\ude32","unicode":"U+1F632","name":"astonished face"},"flushed":{"shortname":"flushed","emoji":"\ud83d\ude33","unicode":"U+1F633","name":"flushed face"},"sleeping":{"shortname":"sleeping","emoji":"\ud83d\ude34","unicode":"U+1F634","name":"sleeping face"},"dizzy_face":{"shortname":"dizzy_face","emoji":"\ud83d\ude35","unicode":"U+1F635","name":"dizzy face"},"no_mouth":{"shortname":"no_mouth","emoji":"\ud83d\ude36","unicode":"U+1F636","name":"face without mouth"},"mask":{"shortname":"mask","emoji":"\ud83d\ude37","unicode":"U+1F637","name":"face with medical mask"},"smile_cat":{"shortname":"smile_cat","emoji":"\ud83d\ude38","unicode":"U+1F638","name":"grinning cat face with smiling eyes"},"joy_cat":{"shortname":"joy_cat","emoji":"\ud83d\ude39","unicode":"U+1F639","name":"cat face with tears of joy"},"smiley_cat":{"shortname":"smiley_cat","emoji":"\ud83d\ude3a","unicode":"U+1F63A","name":"smiling cat face with open mouth"},"heart_eyes_cat":{"shortname":"heart_eyes_cat","emoji":"\ud83d\ude3b","unicode":"U+1F63B","name":"smiling cat face with heart-shaped eyes"},"smirk_cat":{"shortname":"smirk_cat","emoji":"\ud83d\ude3c","unicode":"U+1F63C","name":"cat face with wry smile"},"kissing_cat":{"shortname":"kissing_cat","emoji":"\ud83d\ude3d","unicode":"U+1F63D","name":"kissing cat face with closed eyes"},"pouting_cat":{"shortname":"pouting_cat","emoji":"\ud83d\ude3e","unicode":"U+1F63E","name":"pouting cat face"},"crying_cat_face":{"shortname":"crying_cat_face","emoji":"\ud83d\ude3f","unicode":"U+1F63F","name":"crying cat face"},"scream_cat":{"shortname":"scream_cat","emoji":"\ud83d\ude40","unicode":"U+1F640","name":"weary cat face"},"no_good":{"shortname":"no_good","emoji":"\ud83d\ude45","unicode":"U+1F645","name":"face with no good gesture"},"ok_woman":{"shortname":"ok_woman","emoji":"\ud83d\ude46","unicode":"U+1F646","name":"face with ok gesture"},"bow":{"shortname":"bow","emoji":"\ud83d\ude47","unicode":"U+1F647","name":"person bowing deeply"},"see_no_evil":{"shortname":"see_no_evil","emoji":"\ud83d\ude48","unicode":"U+1F648","name":"see-no-evil monkey"},"hear_no_evil":{"shortname":"hear_no_evil","emoji":"\ud83d\ude49","unicode":"U+1F649","name":"hear-no-evil monkey"},"speak_no_evil":{"shortname":"speak_no_evil","emoji":"\ud83d\ude4a","unicode":"U+1F64A","name":"speak-no-evil monkey"},"raising_hand":{"shortname":"raising_hand","emoji":"\ud83d\ude4b","unicode":"U+1F64B","name":"happy person raising one hand"},"raised_hands":{"shortname":"raised_hands","emoji":"\ud83d\ude4c","unicode":"U+1F64C","name":"person raising both hands in celebration"},"person_frowning":{"shortname":"person_frowning","emoji":"\ud83d\ude4d","unicode":"U+1F64D","name":"person frowning"},"person_with_pouting_face":{"shortname":"person_with_pouting_face","emoji":"\ud83d\ude4e","unicode":"U+1F64E","name":"person with pouting face"},"pray":{"shortname":"pray","emoji":"\ud83d\ude4f","unicode":"U+1F64F","name":"person with folded hands"},"rocket":{"shortname":"rocket","emoji":"\ud83d\ude80","unicode":"U+1F680","name":"rocket"},"helicopter":{"shortname":"helicopter","emoji":"\ud83d\ude81","unicode":"U+1F681","name":"helicopter"},"steam_locomotive":{"shortname":"steam_locomotive","emoji":"\ud83d\ude82","unicode":"U+1F682","name":"steam locomotive"},"railway_car":{"shortname":"railway_car","emoji":"\ud83d\ude83","unicode":"U+1F683","name":"railway car"},"bullettrain_side":{"shortname":"bullettrain_side","emoji":"\ud83d\ude84","unicode":"U+1F684","name":"high-speed train"},"bullettrain_front":{"shortname":"bullettrain_front","emoji":"\ud83d\ude85","unicode":"U+1F685","name":"high-speed train with bullet nose"},"train2":{"shortname":"train2","emoji":"\ud83d\ude86","unicode":"U+1F686","name":"train"},"metro":{"shortname":"metro","emoji":"\ud83d\ude87","unicode":"U+1F687","name":"metro"},"light_rail":{"shortname":"light_rail","emoji":"\ud83d\ude88","unicode":"U+1F688","name":"light rail"},"station":{"shortname":"station","emoji":"\ud83d\ude89","unicode":"U+1F689","name":"station"},"tram":{"shortname":"tram","emoji":"\ud83d\ude8a","unicode":"U+1F68A","name":"tram"},"train":{"shortname":"train","emoji":null,"unicode":"U+1F68B","name":"tram car"},"bus":{"shortname":"bus","emoji":"\ud83d\ude8c","unicode":"U+1F68C","name":"bus"},"oncoming_bus":{"shortname":"oncoming_bus","emoji":"\ud83d\ude8d","unicode":"U+1F68D","name":"oncoming bus"},"trolleybus":{"shortname":"trolleybus","emoji":"\ud83d\ude8e","unicode":"U+1F68E","name":"trolleybus"},"busstop":{"shortname":"busstop","emoji":"\ud83d\ude8f","unicode":"U+1F68F","name":"bus stop"},"minibus":{"shortname":"minibus","emoji":"\ud83d\ude90","unicode":"U+1F690","name":"minibus"},"ambulance":{"shortname":"ambulance","emoji":"\ud83d\ude91","unicode":"U+1F691","name":"ambulance"},"fire_engine":{"shortname":"fire_engine","emoji":"\ud83d\ude92","unicode":"U+1F692","name":"fire engine"},"police_car":{"shortname":"police_car","emoji":"\ud83d\ude93","unicode":"U+1F693","name":"police car"},"oncoming_police_car":{"shortname":"oncoming_police_car","emoji":"\ud83d\ude94","unicode":"U+1F694","name":"oncoming police car"},"taxi":{"shortname":"taxi","emoji":"\ud83d\ude95","unicode":"U+1F695","name":"taxi"},"oncoming_taxi":{"shortname":"oncoming_taxi","emoji":"\ud83d\ude96","unicode":"U+1F696","name":"oncoming taxi"},"car":{"shortname":"car","emoji":"\ud83d\ude97","unicode":"U+1F697","name":"automobile"},"oncoming_automobile":{"shortname":"oncoming_automobile","emoji":"\ud83d\ude98","unicode":"U+1F698","name":"oncoming automobile"},"blue_car":{"shortname":"blue_car","emoji":"\ud83d\ude99","unicode":"U+1F699","name":"recreational vehicle"},"truck":{"shortname":"truck","emoji":"\ud83d\ude9a","unicode":"U+1F69A","name":"delivery truck"},"articulated_lorry":{"shortname":"articulated_lorry","emoji":"\ud83d\ude9b","unicode":"U+1F69B","name":"articulated lorry"},"tractor":{"shortname":"tractor","emoji":"\ud83d\ude9c","unicode":"U+1F69C","name":"tractor"},"monorail":{"shortname":"monorail","emoji":"\ud83d\ude9d","unicode":"U+1F69D","name":"monorail"},"mountain_railway":{"shortname":"mountain_railway","emoji":"\ud83d\ude9e","unicode":"U+1F69E","name":"mountain railway"},"suspension_railway":{"shortname":"suspension_railway","emoji":"\ud83d\ude9f","unicode":"U+1F69F","name":"suspension railway"},"mountain_cableway":{"shortname":"mountain_cableway","emoji":"\ud83d\udea0","unicode":"U+1F6A0","name":"mountain cableway"},"aerial_tramway":{"shortname":"aerial_tramway","emoji":"\ud83d\udea1","unicode":"U+1F6A1","name":"aerial tramway"},"ship":{"shortname":"ship","emoji":"\ud83d\udea2","unicode":"U+1F6A2","name":"ship"},"rowboat":{"shortname":"rowboat","emoji":"\ud83d\udea3","unicode":"U+1F6A3","name":"rowboat"},"speedboat":{"shortname":"speedboat","emoji":"\ud83d\udea4","unicode":"U+1F6A4","name":"speedboat"},"traffic_light":{"shortname":"traffic_light","emoji":"\ud83d\udea5","unicode":"U+1F6A5","name":"horizontal traffic light"},"vertical_traffic_light":{"shortname":"vertical_traffic_light","emoji":"\ud83d\udea6","unicode":"U+1F6A6","name":"vertical traffic light"},"construction":{"shortname":"construction","emoji":"\ud83d\udea7","unicode":"U+1F6A7","name":"construction sign"},"rotating_light":{"shortname":"rotating_light","emoji":"\ud83d\udea8","unicode":"U+1F6A8","name":"police cars revolving light"},"triangular_flag_on_post":{"shortname":"triangular_flag_on_post","emoji":"\ud83d\udea9","unicode":"U+1F6A9","name":"triangular flag on post"},"door":{"shortname":"door","emoji":"\ud83d\udeaa","unicode":"U+1F6AA","name":"door"},"no_entry_sign":{"shortname":"no_entry_sign","emoji":"\ud83d\udeab","unicode":"U+1F6AB","name":"no entry sign"},"smoking":{"shortname":"smoking","emoji":"\ud83d\udeac","unicode":"U+1F6AC","name":"smoking symbol"},"no_smoking":{"shortname":"no_smoking","emoji":"\ud83d\udead","unicode":"U+1F6AD","name":"no smoking symbol"},"put_litter_in_its_place":{"shortname":"put_litter_in_its_place","emoji":"\ud83d\udeae","unicode":"U+1F6AE","name":"put litter in its place symbol"},"do_not_litter":{"shortname":"do_not_litter","emoji":"\ud83d\udeaf","unicode":"U+1F6AF","name":"do not litter symbol"},"potable_water":{"shortname":"potable_water","emoji":"\ud83d\udeb0","unicode":"U+1F6B0","name":"potable water symbol"},"non-potable_water":{"shortname":"non-potable_water","emoji":"\ud83d\udeb1","unicode":"U+1F6B1","name":"non-potable water symbol"},"bike":{"shortname":"bike","emoji":"\ud83d\udeb2","unicode":"U+1F6B2","name":"bicycle"},"no_bicycles":{"shortname":"no_bicycles","emoji":"\ud83d\udeb3","unicode":"U+1F6B3","name":"no bicycles"},"bicyclist":{"shortname":"bicyclist","emoji":"\ud83d\udeb4","unicode":"U+1F6B4","name":"bicyclist"},"mountain_bicyclist":{"shortname":"mountain_bicyclist","emoji":"\ud83d\udeb5","unicode":"U+1F6B5","name":"mountain bicyclist"},"walking":{"shortname":"walking","emoji":"\ud83d\udeb6","unicode":"U+1F6B6","name":"pedestrian"},"no_pedestrians":{"shortname":"no_pedestrians","emoji":"\ud83d\udeb7","unicode":"U+1F6B7","name":"no pedestrians"},"children_crossing":{"shortname":"children_crossing","emoji":"\ud83d\udeb8","unicode":"U+1F6B8","name":"children crossing"},"mens":{"shortname":"mens","emoji":"\ud83d\udeb9","unicode":"U+1F6B9","name":"mens symbol"},"womens":{"shortname":"womens","emoji":"\ud83d\udeba","unicode":"U+1F6BA","name":"womens symbol"},"restroom":{"shortname":"restroom","emoji":"\ud83d\udebb","unicode":"U+1F6BB","name":"restroom"},"baby_symbol":{"shortname":"baby_symbol","emoji":"\ud83d\udebc","unicode":"U+1F6BC","name":"baby symbol"},"toilet":{"shortname":"toilet","emoji":"\ud83d\udebd","unicode":"U+1F6BD","name":"toilet"},"wc":{"shortname":"wc","emoji":"\ud83d\udebe","unicode":"U+1F6BE","name":"water closet"},"shower":{"shortname":"shower","emoji":"\ud83d\udebf","unicode":"U+1F6BF","name":"shower"},"bath":{"shortname":"bath","emoji":"\ud83d\udec0","unicode":"U+1F6C0","name":"bath"},"bathtub":{"shortname":"bathtub","emoji":"\ud83d\udec1","unicode":"U+1F6C1","name":"bathtub"},"passport_control":{"shortname":"passport_control","emoji":"\ud83d\udec2","unicode":"U+1F6C2","name":"passport control"},"customs":{"shortname":"customs","emoji":"\ud83d\udec3","unicode":"U+1F6C3","name":"customs"},"baggage_claim":{"shortname":"baggage_claim","emoji":"\ud83d\udec4","unicode":"U+1F6C4","name":"baggage claim"},"left_luggage":{"shortname":"left_luggage","emoji":"\ud83d\udec5","unicode":"U+1F6C5","name":"left luggage"},"hash":{"shortname":"hash","emoji":null,"unicode":"U+0023-20E3","name":"hash key"},"zero":{"shortname":"zero","emoji":null,"unicode":"U+0030-20E3","name":"keycap 0"},"one":{"shortname":"one","emoji":null,"unicode":"U+0031-20E3","name":"keycap 1"},"two":{"shortname":"two","emoji":null,"unicode":"U+0032-20E3","name":"keycap 2"},"three":{"shortname":"three","emoji":null,"unicode":"U+0033-20E3","name":"keycap 3"},"four":{"shortname":"four","emoji":null,"unicode":"U+0034-20E3","name":"keycap 4"},"five":{"shortname":"five","emoji":null,"unicode":"U+0035-20E3","name":"keycap 5"},"six":{"shortname":"six","emoji":null,"unicode":"U+0036-20E3","name":"keycap 6"},"seven":{"shortname":"seven","emoji":null,"unicode":"U+0037-20E3","name":"keycap 7"},"eight":{"shortname":"eight","emoji":null,"unicode":"U+0038-20E3","name":"keycap 8"},"nine":{"shortname":"nine","emoji":null,"unicode":"U+0039-20E3","name":"keycap 9"},"cn":{"shortname":"cn","emoji":null,"unicode":"U+1F1E8-1F1F3","name":"regional indicator symbol letters cn"},"de":{"shortname":"de","emoji":null,"unicode":"U+1F1E9-1F1EA","name":"regional indicator symbol letters de"},"es":{"shortname":"es","emoji":null,"unicode":"U+1F1EA-1F1F8","name":"regional indicator symbol letters es"},"fr":{"shortname":"fr","emoji":null,"unicode":"U+1F1EB-1F1F7","name":"regional indicator symbol letters fr"},"gb":{"shortname":"gb","emoji":null,"unicode":"U+1F1EC-1F1E7","name":"regional indicator symbol letters gb"},"it":{"shortname":"it","emoji":null,"unicode":"U+1F1EE-1F1F9","name":"regional indicator symbol letters it"},"jp":{"shortname":"jp","emoji":null,"unicode":"U+1F1EF-1F1F5","name":"regional indicator symbol letters jp"},"kr":{"shortname":"kr","emoji":null,"unicode":"U+1F1F0-1F1F7","name":"regional indicator symbol letters kr"},"ru":{"shortname":"ru","emoji":null,"unicode":"U+1F1F7-1F1FA","name":"regional indicator symbol letters ru"},"us":{"shortname":"us","emoji":null,"unicode":"U+1F1FA-1F1F8","name":"regional indicator symbol letters us"}}